[{"i":107702,"h":"ﬁzz","b":"[noun] ; फज (शोर)"},{"i":107710,"h":"ﬁzzle","b":"[verb] ; फजल होब ( वफल)"},{"i":107713,"h":"ﬁzzy","b":"[adj.] ; फजी (पेय)"},{"i":107714,"h":"ﬁzzy drink","b":"[noun] ; काबानेटेड पेय (सोडा)"},{"i":311074,"h":"Z","b":"Z, अं ेजी वणमालाक छ बीसम आ अं तम अ र, एकटा वर- ंजन अ छ। ई लै टन Z सँ लेल गेल, जे ीक वणमालासँ आयल, जा हमे ई सेमे टक ोतसँ आयल। अं तम उ प संभवतः म ी अ छ।"},{"i":311075,"h":"Z","b":"अं ेजी वणमालाक छ बीसम आ अं तम अ र"},{"i":311076,"h":"z","b":"स ता नबे"},{"i":311077,"h":"Z liberated fax","b":"[adj.] ; वमु त"},{"i":311078,"h":"Z ocal","b":"[n.] ; दः ञोभ"},{"i":311079,"h":"Z, z","b":"[noun] ; ज़ेड"},{"i":311080,"h":"z-axis","b":"[n] ; ल-अ , ला"},{"i":311081,"h":"Z00","b":"[n.] ; च डयाखाना"},{"i":311082,"h":"Za","b":"[n.] ; B लैटक लेल एकटा पुरान सॉलफ े जयो नाम; सातम हामा नक, जेना ईओ लयन तारमे सुनल जाइत अ छ; — टा टनी ारा ए ह नामसँ बुलाओल गेल।"},{"i":311083,"h":"ZA ve. 0 3 convince","b":"राजी करब"},{"i":311084,"h":"ZA ve. to thin OY","b":"-8 - खटकाएब"},{"i":311085,"h":"ZA vs. to change words","b":"वात फ े रब"},{"i":311086,"h":"Zabaism","b":"[n.] ; जै ब मक अ य प"},{"i":311087,"h":"Zabian","b":"[a. & n.] ; से बयन देखू।"},{"i":311088,"h":"Zabism","b":"[n.] ; से बय न म देखू।"},{"i":311089,"h":"Zacco","b":"[n.] ; जो को देखू।"},{"i":311090,"h":"Zachun","b":"[n.] ; अरब ारा एकटा छोट काँटेदार पेड़ (बैलेनाइट्स ए ज टयाका)क फलसँ दबायल एकटा तेल, जे या ीक उपचार मलहमक पमे बेचल जाइत अ छ।"},{"i":311091,"h":"Zaerthe","b":"[n.] ; जारथेक समान।"},{"i":311092,"h":"Zaﬀer","b":"[n.] ; एकटा रंजक जे सामा यतः कोबा ट ले सक बालु वा वाट्जसँ भूनक गहरा म ी-समान चूणक पमे ा त कयल जाइत अ छ। एकरा पो सलेन- च ण आ ु हार -इनेम लगमे नीला रंग बनाबय लेल यु त कयल जाइत अ छ।"},{"i":311093,"h":"Zaim","b":"[n.] ; एकटा तुक मुख जे ए हये नामक घुड़सवार म ल शयाक समथन देइत अ छ।"},{"i":311094,"h":"Zaimet","b":"[n.] ; एकटा जला जा हसँ जाइम अपन राज व लैत अ छ।"},{"i":311095,"h":"Zain","b":"[n.] ; गहरा रंगक एकटा घोड़ा, न धूसर न सफ े द, आ बना कोनो ध बाक।"},{"i":311096,"h":"Zalambdodont","b":"[a.] ; इ से टवोराक एकटा जनजा त (जैलै बडोडो टा)सँ संबं धत जा हमे दाढ़क क े वल एकटा V-आकार उभार होइत छैक।"},{"i":311097,"h":"Zalambdodont","b":"[n.] ; जैलै बडोडो टामेसँ एकटा। टे ेक, सोलेनोडोन, आ व णम तल उदाहरण अ छ।"},{"i":311098,"h":"Zamang","b":"[n.] ; वेनेजुएलाक एकटा वशाल फलीदार पेड़ ( पथेकोलो बयम सैमन)। एकर शाखा ायः एक सौ अ सी फ ू ट चौड़ा अधगोलाकार समूह बनबैत अ छ। मीठा गूदेदार फली सामा यतः पशुक खुएयमे यु त। वषा-पेड़ सेहो कहल जाइत अ छ।"},{"i":311099,"h":"Zambo","b":"[n.] ; मुलाटो आ नी ोक ब चा; सेहो, भारतीय आ नी ोक ब चा; बोलचालमे वा हा यमे नी ो; सै बो।"},{"i":311100,"h":"Zambos","b":"[pl.] ; जै बोक"},{"i":311101,"h":"Zamia","b":"[n.] ; साइक े डे सयस पादपक एकटा जा त, नीचा ताड़ जेकाँ देखावट यु त, मुदा ए सोजेनस काठ यु त। ूं टी देखू।"},{"i":311102,"h":"Zamindar","b":"[n.] ; एकटा भू वामी; सेहो, भू म-राज व सं ाहक; अखन, सामा यतः, एकटा कारक सामंत जे जाइध र सरकारक न त राज व देइत अ छ ताइध र वा त वक मा लक मानल जाइत अ छ।"},{"i":311103,"h":"zamindar","b":"[n.] ; ज मदार"},{"i":311104,"h":"Zamindari","b":"[n.] ; जम दारक े ा धकार; जम दार ारा धा रत भू म।"},{"i":311105,"h":"Zamindary","b":"[n.] ; जम दार क अ य प"},{"i":311106,"h":"Zamite","b":"[n.] ; जा मया जा तक एकटा जीवा म साइक े ड।"},{"i":311107,"h":"Zamouse","b":"[n.] ; एकटा प म अ क भस (बुबेलस ेक सेरोस) जा हमे आधारमे दबल छोट स ग आ तीन पं त ल बा रोमसँ भीतरसँ कना रत बड़का कान होइत छैक। लटकन र हत। छोट-स गवाला भस आ झाड़ -गाय सेहो कहल जाइत अ छ।"},{"i":311108,"h":"Zampogna","b":"[n.] ; प हने इटा लयन कसानोमे च लत एकटा कारक बैगपाइप। आब लगभग अ च लत।"},{"i":311109,"h":"Zander","b":"[n.] ; एकटा यूरोपीय पाइक पच ( टजो टे डयन ू सयोपका) जो वाल-आईसँ संबं धत अ छ।"},{"i":311110,"h":"Zandmole","b":"[n.] ; बालू- तल।"},{"i":311111,"h":"Zanies","b":"[pl.] ; जेनीक"},{"i":311112,"h":"Zante","b":"[n.] ; जै टेवूड देखू।"},{"i":311113,"h":"Zante currant","b":"एकटा कारक बीजर हत अंगूर वा कश मश — जै टे, आयो नयन ीपमेसँ एकटा, सँ ए ह नामसँ जानल जाइत अ छ।"},{"i":311114,"h":"Zantewood","b":"[n.] ; एकटा पीला रंग-काठ; फ टेट; — जै टे आ जै टे फ टक सेहो कहल जाइत अ छ। फ टेट आ फ टकक अ तगत ट पणी देखू।"},{"i":311115,"h":"Zantewood","b":"[n.] ; साटनवूड ( लोरोजाइलन वटे नया)।"},{"i":311116,"h":"Zantiot","b":"[n.] ; जै टेक, आयो नयन ीपसमूहमेसँ एकटाक, मूल नवासी वा रहयवाला।"},{"i":311117,"h":"zany","b":"[adj.] ; पागल (सनक )"},{"i":311118,"h":"Zany","b":"[n.] ; एकटा मेर -ए ड; एकटा व षक।"},{"i":311119,"h":"Zany","b":"[n.] ; सहायक"},{"i":311120,"h":"Zany","b":"[v. t.] ; नकल उतारब।"},{"i":311121,"h":"Zanyism","b":"[n.] ; जेनीक च र वा आचरण; व षकपन।"},{"i":311122,"h":"zap","b":"[verb] ; तेज ग त जाब (भाग)"},{"i":311123,"h":"zap","b":"[verb] ; मारब (न )"},{"i":311124,"h":"Zaphara","b":"[n.] ; जैफर।"},{"i":311125,"h":"Zaphrentis","b":"[n.] ; साइआथोफाइलॉइड वालक एकटा वलु त जा त जे पुराजीवी न ेपमे सामा य अ छ। ई याला-आक ृ त, अनेक प ीयु त, आ यालाक एकठाम गहरा ग ेयु त अ छ।"},{"i":311126,"h":"Zapotilla","b":"[n.] ; सैपो डला देखू।"},{"i":311127,"h":"Zaptiah","b":"[n.] ; एकटा तुक पु लसकम ।"},{"i":311128,"h":"Zarathustrian","b":"[a.] ; जरथु कक अ य प"},{"i":311129,"h":"Zarathustric","b":"[a.] ; जरथु , वा जरथु वाद, जरथु सँ संबं धत।"},{"i":311130,"h":"Zarathustrism","b":"[n.] ; जरथु वाद देखू।"},{"i":311131,"h":"Zaratite","b":"[n.] ; ोमाइटपर प ना-ह रत पपड़ क पमे पाओल जायवाला नक े लक जलयु त काबानेट; — प ना नक े ल सेहो कहल जाइत अ छ।"},{"i":311132,"h":"Zareba","b":"[n.] ; एकटा ता का लक पसँ बनाओल बाड़ा; वशेषतः, काँटेदार झाड़ सँ बनल।"},{"i":311133,"h":"Zarnich","b":"[n.] ; आस नकक मूल स फाइड, जा हमे सै डेरेक वा रयलगर, आ ओर पमट शा मल अ छ।"},{"i":311134,"h":"Zarthe","b":"[n.] ; एकटा यूरोपीय ीम (अ ा मस व बा)।"},{"i":311135,"h":"Zati","b":"[n.] ; मकाकक एकटा जा त (मकाकस पलेटस) भारत आ सीलोनक मूल नवासी। ए हमे ल बा सीधा रोमक एकटा मुक ु ट आ सरक पाछूमे वक ण रोमक गु ा होइत छैक।"},{"i":311136,"h":"Zauschneria","b":"[n.] ; फ ू लदार पादपक एकटा जा त। जाउ ने रया क ै लफो नका एकटा अधझाड़ य ब वष य अ छ जा हमे बगीचाक फ ू शयासँ मलैत-जुलैत सु दर लाल फ ू ल होइत छैक।"},{"i":311137,"h":"Zax","b":"[n.] ; छत- लेट काटब आ छेद करयबला एकटा औजार।"},{"i":311138,"h":"Zayat","b":"[n.] ; या ी, उपासक आ दक लेल एकटा सावज नक छाजन वा बरामदा।"},{"i":311139,"h":"ze","b":"[vi.] ; ज मा हएब"},{"i":311140,"h":"Ze tattii","b":"[n.] ; टटोरब"},{"i":311141,"h":"Zea","b":"[n.] ; बड़का घासक एकटा जा त जा हमे भारतीय मकई ( जया मेज) एकमा ात जा त अ छ। एकर उ प अखन तक था पत न ह भेल अ छ। मकई देखू।"},{"i":311142,"h":"Zeal","b":"[n.] ; उ साह"},{"i":311143,"h":"Zeal","b":"[n.] ; उ साह / उमङ ् ग / लगन / जोश"},{"i":311144,"h":"zeal","b":"[n.] ; उ सुकता"},{"i":311145,"h":"Zeal","b":"[n.] ; एकटा जोशीला त।"},{"i":311146,"h":"Zeal","b":"[n.] ; कसी व तुक खोजमे भावा मक उ साह; कसी त वा कारणक प मे उ क ं ठा; ती आ स य च; त मयता; उ साह; जोश।"},{"i":311147,"h":"zeal","b":"[n.] ; धु"},{"i":311148,"h":"zeal","b":"[n.] ; ता"},{"i":311149,"h":"zeal","b":"[noun] ; जोश (उ साह)"},{"i":311150,"h":"Zeal","b":"[v. i.] ; उ साही होयब।"},{"i":311151,"h":"zeal illustratation","b":"[n.] ; उदाहरण"},{"i":311152,"h":"Zealant","b":"[n.] ; ओ त जे उ साही अ छ; एकटा जोशीला; एकटा उ साही।"},{"i":311153,"h":"Zealed","b":"[a.] ; उ साहसँ प रपूण; उ साहक वशेषता यु त।"},{"i":311154,"h":"Zealful","b":"[a.] ; उ साहसँ प रपूण।"},{"i":311155,"h":"Zealless","b":"[a.] ; उ साहर हत।"},{"i":311156,"h":"Zealot","b":"[n.] ; अ त"},{"i":311157,"h":"Zealot","b":"[n.] ; ओ त जे उ साही अ छ; जे कसी कारणमे गमजोशीसँ भाग लैत अ छ आ अपन उ े य त परतासँ आगू बढ़बैत अ छ; वशेषतः ओ जे अ त-उ साही अ छ; कसी वषयमे त लीन; उ साही; क र प धर।"},{"i":311158,"h":"Zealot","b":"[n.] ; क प थी / हठधम / अ धभ त"},{"i":311159,"h":"zealot","b":"[n.] ; धमा धता"},{"i":311160,"h":"zealot","b":"[noun] ; क रपंथी (उ )"},{"i":311161,"h":"zealot","b":"[vt.] ; सब"},{"i":311162,"h":"Zealotical","b":"[a.] ; जोशीलाक समान वा उपयु त; उ कटतासँ उ साही।"},{"i":311163,"h":"Zealotism","b":"[n.] ; जोशीलाक च र वा आचरण; क रपंथ।"},{"i":311164,"h":"Zealotist","b":"[n.] ; एकटा जोशीला।"},{"i":311165,"h":"Zealotry","b":"[n.] ; जोशीलाक च र आ वहार; उ साहक अ तरेक; कसी कारणक लेल क र भ त।"},{"i":311166,"h":"Zealous","b":"[a.] ; उ साहसँ प रपूण वा ओकर वशेषता यु त; कसी व तुक प मे गमजोशीसँ संल न वा उ साही।"},{"i":311167,"h":"Zealous","b":"[a.] ; उ साही / लगनशील / जोश सं भरल"},{"i":311168,"h":"Zealous","b":"[a.] ; धा मक उ साहसँ प रपूण।"},{"i":311169,"h":"zealous","b":"[adj.] ; उ साही (जोशीला)"},{"i":311170,"h":"zealous","b":"[adj.] ; उ सुक"},{"i":311171,"h":"zealous","b":"[adj.] ; तवादी"},{"i":311172,"h":"zealous","b":"[adj.] ;"},{"i":311173,"h":"Zebec","b":"[n.] ; जेबेक देखू।"},{"i":311174,"h":"Zebra","b":"[n.] ; जेबरा / च ीदार जङ ् गली घोड़ा"},{"i":311175,"h":"Zebra","b":"[n.] ; जे ा"},{"i":311176,"h":"Zebra","b":"[n.] ; द ण अ काक जा तक जंगली घोड़ामेसँ कोनो एकटा जे शर रपर सफ े द वा पीताभ सफ े द आ गहरा भूरा वा काला धार सँ उ लेखनीय अ छ।"},{"i":311177,"h":"zebra","b":"[noun] ; ज़ेबरा (जानवर)"},{"i":311178,"h":"zebra","b":"[noun] ; जे ा"},{"i":311179,"h":"zebra crossing","b":"[noun] ; ज़ेबरा ॉ सग (सड़क)"},{"i":311180,"h":"Zebrawood","b":"[n.] ; एकटा छोट वे ट इंड ज मट सयस पेड़ (यूजे नया े े स)क लकड़ ।"},{"i":311181,"h":"Zebrawood","b":"[n.] ; एकटा कारक अलमार -काठ जा हमे सु दर काला, भूरा आ सफ े दाहट धार होइत छैक, एकटा उ णक टबंधीय अमे रक पेड़ (कोनारस गायने सस)क लकड़ ।"},{"i":311182,"h":"Zebrawood","b":"[n.] ; गुयेटाडा जा तक एकटा पूव भारतीय पेड़क लकड़ ।"},{"i":311183,"h":"Zebrine","b":"[a.] ; ज़े ासँ संबं धत वा ओकर समान।"},{"i":311184,"h":"Zebu","b":"[n.] ; कक ु ान बरद / हमर देशी साँढ़"},{"i":311185,"h":"Zebu","b":"[n.] ; पलुआ साँड़"},{"i":311186,"h":"Zebu","b":"[n.] ; भारत, चीन, पूव ीपसमूह आ पूव अ कामे ापक पसँ पालतू एकटा गोजातीय तनपायी (बॉस इं डकस)। एकर सामा यतः छोट स ग, बड़का लटकल कान, पातर टाँग, बड़का लटकन, आ का हपर बड़का उभरल ू बड़ होइत छैक।"},{"i":311187,"h":"Zebub","b":"[n.] ; अबीसी नयाक एकटा बड़का हा नकर म खी जे सेसी म खीक समान पशुक लेल हा नकारक अ छ।"},{"i":311188,"h":"Zechin","b":"[n.] ; सी वन देखू।"},{"i":311189,"h":"Zechstein","b":"[n.] ; यूरोपक प मयन (डायस)क ऊपर वभाग। मुख च ान मै ने शयन चूनाप थर अ छ।"},{"i":311190,"h":"Zed","b":"[n.] ; Z अ र; — जी सेहो कहल जाइत अ छ, प हने इजाड।"},{"i":311191,"h":"Zedoary","b":"[n.] ; पूव भारतसँ ा त एकटा औषधीय पदाथ, जा हमे सुगं धत गंध आ गम, कड़, सुगं धत वाद होइत छैक। दवाइमे उ ेजक पमे यु त।"},{"i":311192,"h":"Zeekoe","b":"[n.] ; एकटा जलह ती।"},{"i":311193,"h":"Zehner","b":"[n.] ; एकटा ऑ याई चाँदीक स का जे १० ॉय जर वा लगभग ५ सटक बराबर होइत अ छ।"},{"i":311194,"h":"Zein","b":"[n.] ; लूटेनक क ृ तक नाइ ोजनयु त पदाथ, मकई ( ज़या)क बीजसँ मृ , पीताभ, अ पाकार पदाथक पमे ा त।"},{"i":311195,"h":"Zein","b":"[n.] ; भु ाक सार आ ोटीन"},{"i":311196,"h":"zeitgeist","b":"[n.] ; समय चेतना"},{"i":311197,"h":"Zemindar","b":"[n.] ; जम दारक समान।"},{"i":311198,"h":"Zemindari","b":"[n.] ; जम दार क समान।"},{"i":311199,"h":"Zemindary","b":"[n.] ; जम दार क अ य प"},{"i":311200,"h":"Zemni","b":"[n.] ; अंधा छछूंदर-चूहा ( पालै स टाइ लस), पूव यूरोप आ ए शयाक मूल नवासी। एकर आँ ख आ कान अव श , आ रोम मुलायम आ भूरा, कम-बेसी धूसरसँ रं जत होइत छैक।"},{"i":311201,"h":"Zen","b":"[noun] ; ज़ेन (बौ )"},{"i":311202,"h":"Zenana","b":"[n.] ; अंतःपुर"},{"i":311203,"h":"Zenana","b":"[n.] ; एकटा आवासक म हलाआक लेल सुर त भाग।"},{"i":311204,"h":"Zend","b":"[n.] ; वा तवमे, अवे ता, जरथु वादी प व लेखनक, वारेश वा सा ह यक प वी भाषामे अनुवाद आ ा या; सामा य योगमे, ओ भाषा (एकटा ाचीन फारसी बोली) जा हमे अवे ता लखल गेल अ छ।"},{"i":311205,"h":"Zend-Avesta","b":"[n.] ; जरथु क ेय देल गेल ाचीन फारसी धमक प व लेखन, मुदा अ धकतर बादक त थक।"},{"i":311206,"h":"Zend-Avesta","b":"[noun] ; जद-अवे ता ( ंथ)"},{"i":311207,"h":"Zendik","b":"[n.] ; ना तक वा अ व ासी; — पूवमे ओहन लोकक नाम जनका कसी कट धमक अ व ासक वा जा ई वधमक आरोप लगायल जाइत छल।"},{"i":311208,"h":"Zenick","b":"[n.] ; एकटा द ण अ क बल खनयवाला तनपायी (सु रकाटा टे ाडै टाइला), जे सवेटसँ संबं धत अ छ। सु रक े ट सेहो कहल जाइत अ छ।"},{"i":311209,"h":"Zenik","b":"[n.] ; जे नक देखू।"},{"i":311210,"h":"Zenith","b":"[n.] ; अतः, ला णक पमे, चरमो कषक ब ; सवा च ऊ ँ चाई; सफलता वा समृ क उ चतम थ त।"},{"i":311211,"h":"Zenith","b":"[n.] ; खगोलीय ऊ व ब / चरम सीमा / उ न त कऽ शखर"},{"i":311212,"h":"Zenith","b":"[n.] ; खम य"},{"i":311213,"h":"Zenith","b":"[n.] ; यमान आकाशीय गोलाधमे ओ ब जे दशकक ठ क ऊपर होइत अ छ; आकाशमे ठ क सरपर थत ब — ना डरक वपर त।"},{"i":311214,"h":"zenith","b":"[noun] ; चरम ( शखर)"},{"i":311215,"h":"Zenithal","b":"[a.] ; शखर- ब सँ संबं धत वा ओकर अनु प।"},{"i":311216,"h":"Zeolite","b":"[n.] ; एकटा श द जे ख नजक एक प रवारक दशाबय लेल अखन यु त होइत अ छ, ए ु मनाक जलयु त स लक े ट जा हमे चूना, सोडा, पोटाश, वा कम लभ बेराइटा होइत छैक। ए हमे ने ोलाइट, ट बाइट, एना साइम, चाबेजाइट, थॉ सनाइट, हेउलै डाइट, आ द शा मल अ छ।"},{"i":311217,"h":"Zeolitic","b":"[a.] ; जयोलाइटसँ संबं धत वा ओकर अनु प; जयोलाइट यु त वा ओकर समान।"},{"i":311218,"h":"Zeolitiform","b":"[a.] ; जयोलाइटक प यु त।"},{"i":311219,"h":"Zephyr","b":"[n.] ; प मक हवा"},{"i":311220,"h":"Zephyr","b":"[n.] ; प मी पवन; का क पमे, कोनो मृ , कोमल हवा।"},{"i":311221,"h":"Zephyr","b":"[n.] ; म द प छया हवा / अनुक ू ल पवन"},{"i":311222,"h":"zephyr","b":"[noun] ; ह क हवा (मंद)"},{"i":311223,"h":"Zephyrus","b":"[n.] ; प मी पवन, वा जेफायर; — सामा यतः त पत आ सभ वनदेवताआमे सवा धक कोमल मानल जाइत अ छ।"},{"i":311224,"h":"Zequin","b":"[n.] ; सी वन देखू।"},{"i":311225,"h":"Zerda","b":"[n.] ; फ े नेक।"},{"i":311226,"h":"Zeriba","b":"[n.] ; जरेबाक समान।"},{"i":311227,"h":"Zero","b":"[n.] ; ओ ब जा हसँ कसी पैमानाक, जेना थमामीटरक, नातक शु होइत अ छ।"},{"i":311228,"h":"Zero","b":"[n.] ; ला णक: सबसँ नचला ब ; थकानक ब ; जेना, नकर धैय लगभग शू यपर प ँच गेल।"},{"i":311229,"h":"Zero","b":"[n.] ; शू य"},{"i":311230,"h":"Zero","b":"[n.] ; शू य / स फर / कछ नह"},{"i":311231,"h":"Zero","b":"[n.] ; शू य; कछु न ह; नाउट।"},{"i":311232,"h":"zero","b":"[noun] ; क (ल य)"},{"i":311233,"h":"zero","b":"[noun] ; ब क ु ल (कोनो नई)"},{"i":311234,"h":"zero","b":"[noun] ; शू य (सं या)"},{"i":311235,"h":"zero","b":"[num.] ; शू य"},{"i":311236,"h":"zero","b":"[num.] ; सु ना"},{"i":311237,"h":"zero alternant","b":"[adj.] ; शू य प"},{"i":311238,"h":"zero alternant (#.)","b":"[num.] ; शू य"},{"i":311239,"h":"zero alternant a","b":"[n.] ; शू य प रवतन"},{"i":311240,"h":"zero case marking a","b":"[n.] ; शू य वभ त"},{"i":311241,"h":"zero gravity","b":"[noun] ; शू य गु वाकषण (अंत र )"},{"i":311242,"h":"zero grazing","b":"[noun] ; बना चराई पशु पालन (खेती)"},{"i":311243,"h":"zero hour","b":"[n.] ; अ भयान समय"},{"i":311244,"h":"zero hour","b":"[n.] ; आ भयान समय"},{"i":311245,"h":"zero hour","b":"[n.] ; सङ ् कटकाल"},{"i":311246,"h":"zero hour","b":"[noun] ; शु समय (शु आत)"},{"i":311247,"h":"zero tolerance","b":"[noun] ; ब क ु ल बदा त नई (नी त)"},{"i":311248,"h":"zero-tolerance","b":"[n.] ; शू य-सहनशीलता"},{"i":311249,"h":"Zeroes","b":"[pl.] ; शू यक"},{"i":311250,"h":"zeroism","b":"[n.] ; शू यता"},{"i":311251,"h":"Zeros","b":"[pl.] ; शू यक"},{"i":311252,"h":"Zest","b":"[n.] ; अखरोटक गुठलीक ढकयवाला का ीय, मोट छाल।"},{"i":311253,"h":"Zest","b":"[n.] ; अतः, कछु जे सुखद वाद देइत वा बढ़बैत अ छ, वा वाद वयं; चवधक; सेहो ती आनंद; वाद; उ साह।"},{"i":311254,"h":"Zest","b":"[n.] ; नारंगी आ न बूक छलका"},{"i":311255,"h":"Zest","b":"[n.] ; संतरा वा नीबूक छलकाक एकटा टुकड़ा, वा ए ह छलकासँ नचोड़ल सुगं धत तेल, जे शराब आ दक वाद देयमे यु त।"},{"i":311256,"h":"Zest","b":"[n.] ; वाद / मज़ा / चाव / उ साह"},{"i":311257,"h":"zest","b":"[noun] ; उ साह (जोश)"},{"i":311258,"h":"Zest","b":"[v. t.] ; संतरा, नीबू आ दक छलकाक पातर टुकड़ामे काटब; कसी व तुक सतहपर छलकाक नचोड़ब।"},{"i":311259,"h":"Zest","b":"[v. t.] ; वाद वा सुगंध देब; वाद वा च बढ़ायब।"},{"i":311260,"h":"Zested","b":"[imp. & p. p.] ; जे टक"},{"i":311261,"h":"Zesting","b":"[p. pr. & vb. n.] ; जे टक"},{"i":311262,"h":"Zeta","b":"[n.] ; एकटा ीक अ र जे हमर 'z' अ रक अनु प अ छ।"},{"i":311263,"h":"Zetetic","b":"[a.] ; खोजब; जाँच-पड़ताल ारा आगू बढ़ब।"},{"i":311264,"h":"Zetetic","b":"[n.] ; एकटा खोजी; — परोनवादीमेसँ कछु ारा अपनायल नाम।"},{"i":311265,"h":"Zetetics","b":"[a.] ; बीजग णतक एकटा शाखा जे अ ात रा शक य खोजसँ संबं धत अ छ।"},{"i":311266,"h":"Zeuglodon","b":"[n.] ; वलु त इओसीन ेलक एकटा जा त, जा हक अवशेष खाड़ रा यमे पाओल गेल अ छ। ए ह जा तक शर र ब त ल बा आ पातर आ दाँत चौड़ा आ दाँतेदार छल।"},{"i":311267,"h":"Zeuglodont","b":"जयू लोडो टाक कोनो जा त।"},{"i":311268,"h":"Zeuglodonta","b":"[n. pl.] ; फोकोडो टयाक समान।"},{"i":311269,"h":"Zeugma","b":"[n.] ; एकटा अलंकार जा ह ारा कोनो वशेषण वा या, जे नकटवत श दसँ सहमत होइत अ छ, पूरकक पमे, र थ अ य श दपर सेहो लागू होइत अ छ।"},{"i":311270,"h":"Zeugmatic","b":"[a.] ; जयू मासँ संबं धत वा ओकर वशेषता यु त।"},{"i":311271,"h":"Zeugobranchiata","b":"[n. pl.] ; जाइगो कयाक समान।"},{"i":311272,"h":"Zeus","b":"[n.] ; ीकाक मुख देवता, आ ऊपर जगतक शासक। एकरा जु पटरसँ समीक ृ त कयल गेल।"},{"i":311273,"h":"Zeuzerian","b":"[n.] ; जयूजेरा जा त मूल जा हक ब बी सड शलभक समूहमेसँ कोनो एकटा। ए ह शलभमेसँ कछु आकारमे बड़का होइत अ छ। बकर -शलभ एकटा उदाहरण अ छ।"},{"i":311274,"h":"Zeylanite","b":"[n.] ; सीलानाइट देखू।"},{"i":311275,"h":"ZF 7 pan of a balance","b":"[n.] ; प ला"},{"i":311276,"h":"Zibet","b":"[n.] ; जबेथक अ य प"},{"i":311277,"h":"Zibeth","b":"[n.] ; एकटा मांसाहार तनपायी ( ववेरा जबेथा) जे सवेटसँ नकट संबं धत अ छ।"},{"i":311278,"h":"Ziega","b":"[n.] ; रेनेटक जमावट बंद भेलाक बाद ए स टक अ ल मलायक धसँ बनल दही।"},{"i":311279,"h":"Zietrisikite","b":"[n.] ; एकटा ख नज मोम, ओजोक े राइटसँ मलैत-जुलैत। ई मो डे वयाक जये सकामे पाओल जाइत अ छ।"},{"i":311280,"h":"Zif","b":"[n.] ; य दी धा मक वषक दोसर महीना, जे हमर मईसँ मेल खाइत अ छ।"},{"i":311281,"h":"Zigger","b":"[v. i.] ; जघारक अ य प"},{"i":311282,"h":"Zighyr","b":"[v. i.] ; सकरक समान।"},{"i":311283,"h":"Zigzag","b":"[a.] ; छोट, ती मोड़ यु त; आगूक दशामे इधर-उधर दौड़ब।"},{"i":311284,"h":"Zigzag","b":"[a.] ; टेढ़ -मेढ़ / व / लहरदार"},{"i":311285,"h":"Zigzag","b":"[n.] ; कछु जा हमे छोट मोड़ वा कोण होइत छैक।"},{"i":311286,"h":"Zigzag","b":"[n.] ; टेढ़ा-मेढ़ा लाइनमे चलयवाला एकटा ढाँचा; शेवरोन, वा शेवरोनक म।"},{"i":311287,"h":"Zigzag","b":"[n.] ; टेढ़ा मेढ़ा रेखा"},{"i":311288,"h":"Zigzag","b":"[n.] ; बोयो देखू।"},{"i":311289,"h":"zigzag","b":"[noun] ; टेढ़ा-मेढ़ा (रा ता)"},{"i":311290,"h":"Zigzag","b":"[v. i.] ; जगजैग ढंगसँ चलब; सेहो, जगजैग आक ृ त होयब।"},{"i":311291,"h":"Zigzag","b":"[v. t.] ; छोट मोड़सँ बनायब।"},{"i":311292,"h":"zigzag/wave backstitch","b":"[n.] ; काँटा फोड़ ब खया"},{"i":311293,"h":"Zigzagged","b":"[imp. & p. p.] ; जगजैगक"},{"i":311294,"h":"Zigzaggery","b":"[n.] ; जगजैग होयबाक गुण वा अव था; टेढ़ापन।"},{"i":311295,"h":"Zigzagging","b":"[p. pr. & vb. n.] ; जगजैगक"},{"i":311296,"h":"Zigzaggy","b":"[a.] ; ती मोड़ यु त।"},{"i":311297,"h":"Zilla","b":"[n.] ; एकटा नीचा, क ँ टीला, अधझाड़ , ू सीफ े रस पादप ( जला माया ॉइड् स) जे म क रे ग तानमे पाओल जाइत अ छ। एकर प ी अरब ारा पा नमे उबालक खाओल जाइत अ छ।"},{"i":311298,"h":"zilla","b":"[noun] ; जला ( शासन)"},{"i":311299,"h":"Zillah","b":"[n.] ; एकटा जला वा थानीय वभाग, जेना कसी ांतक।"},{"i":311300,"h":"Zimb","b":"[n.] ; अबीसी नयाक एकटा बड़का, जहर ला, - पंखवाला म खी। ई सेसी म खीसँ मलैत-जुलैत अ छ आ ओ हना पशुक लेल हा नकारक अ छ।"},{"i":311301,"h":"Ziment-water","b":"[n.] ; तामा खानमे पाओल जायवाला एकटा कारक पा न; तामासँ संतृ त पा न।"},{"i":311302,"h":"zinc","b":"[n.] ; ज ता"},{"i":311303,"h":"Zinc","b":"[n.] ; ज ता (धातु)"},{"i":311304,"h":"Zinc","b":"[n.] ; ज ता यशद"},{"i":311305,"h":"Zinc","b":"[n.] ; मै नी शयम-क ै ड मयम वगक एकटा चुर त व, मु यतः ज ता ले ड, थसोनाइट, क ै लामाइन, आ क लनाइट ख नजसँ ा त, एकटा सरलतासँ पघलयवाला नीलाहट सफ े द धातु। तीक Zn। परमाण भार ६४.९।"},{"i":311306,"h":"zinc","b":"[noun] ; ज ता (धातु)"},{"i":311307,"h":"Zinc","b":"[v. t.] ; ज तासँ आ ा दत करब; गै वेनाइज करब।"},{"i":311308,"h":"Zincane","b":"[n.] ; ज ता लोराइड।"},{"i":311309,"h":"Zinced","b":"ज ताक"},{"i":311310,"h":"Zincic","b":"[a.] ; ज तासँ संबं धत, ओकर यु त, वा ओकर समान; जकस।"},{"i":311311,"h":"Zincide","b":"[n.] ; ज ताक एकटा गुण यौ गक।"},{"i":311312,"h":"Zinciferous","b":"[a.] ; ज ता यु त वा ओकर चुर।"},{"i":311313,"h":"Zinciﬁcation","b":"[n.] ; ज ता लगायबाक या वा या; जक क ृ त वा ज तासँ आ ा दत होयबाक अव था; गै वेनाइजेशन।"},{"i":311314,"h":"Zincify","b":"[v. t.] ; ज तासँ आ ा दत वा संतृ त करब।"},{"i":311315,"h":"Zincing","b":"[n.] ; ज ता लगायबाक या वा या; गै वेनाइजेशन।"},{"i":311316,"h":"Zincing","b":"ज ताक"},{"i":311317,"h":"Zincite","b":"[n.] ; मूल ज ता ऑ साइड; एकटा भंगुर, पारभासी ख नज, नारंगी-लाल रंगक; — लाल ज ता अय क आ ज ताक लाल ऑ साइड सेहो कहल जाइत अ छ।"},{"i":311318,"h":"Zincked","b":"[imp. & p. p.] ; ज ताक"},{"i":311319,"h":"Zincking","b":"[n.] ; ज कगक अ य प"},{"i":311320,"h":"Zincking","b":"[p. pr. & vb. n.] ; ज ताक"},{"i":311321,"h":"Zincky","b":"[a.] ; ज तासँ संबं धत, वा ज ताक जेकाँ देखावट यु त।"},{"i":311322,"h":"Zinco-","b":"ज तासँ बनल एकटा संयोजन- प; रसायनमे, ज ताक क तपय गुण यौ गकक त वक पमे दशबैत अ छ। वशेषण पमे सेहो यु त।"},{"i":311323,"h":"Zinco-polar","b":"[a.] ; बैटर मे अ लसँ सामना कयल ज ताक सतहक समान व ुतीय पसँ वीक ृ त।"},{"i":311324,"h":"Zincode","b":"[n.] ; व ुत-अपघटन को शकाक धना मक इले ोड; एनोड।"},{"i":311325,"h":"Zincographer","b":"[n.] ; ज तापर उ क णन करयवाला कलाकार।"},{"i":311326,"h":"Zincography","b":"[n.] ; ज तापर उ क णन वा अ ल- न काशीक कला वा या, जा हमे आक ृ त काठ-कटाईक शैलीमे उभरल रहैत अ छ आ बाक भू म अ लसँ काटल जाइत अ छ।"},{"i":311327,"h":"Zincoid","b":"[a.] ; ज तासँ संबं धत, ओकर समान — वो टाइक च मे ता -प कसँ जुड़ल ज ता-प कक व ुतक संद भत; धना मक वक संक े त सेहो करैत अ छ।"},{"i":311328,"h":"Zincongraphic","b":"[a.] ; जको ा फकलक अ य प"},{"i":311329,"h":"Zincongraphical","b":"[a.] ; जको ाफ सँ संबं धत वा ओकर अनु प।"},{"i":311330,"h":"Zincous","b":"[a.] ; अतः, प हने, ार य, बेसाइलस, जे लोरसक वपर त अ छ।"},{"i":311331,"h":"Zincous","b":"[a.] ; गै व नक बैटर क धना मक वसँ संबं धत वा ओकर अनु प; व ुत-धना मक।"},{"i":311332,"h":"Zincous","b":"[a.] ; ज तासँ संबं धत, ओकरमे व मान, वा ओकर यु त; ज कक; जेना ज ताक लवण।"},{"i":311333,"h":"zine","b":"[n.] ; ज ता"},{"i":311334,"h":"Zingari","b":"[pl.] ; जगारोक"},{"i":311335,"h":"Zingaro","b":"[n.] ; एकटा ज सी।"},{"i":311336,"h":"Zingel","b":"[n.] ; एकटा छोट, खा , मीठापा नक यूरोपीय पच (ए ो जगेल), जेकर शर र गोल आ ल बाकार आ थूथन उभरल होइत अ छ।"},{"i":311337,"h":"Zingiberaceous","b":"[a.] ; अदरख, वा साइटा मनी मक ए डोजेनस पादपक एकटा जनजा त ( ज जबेर )सँ संबं धत वा ओकर अनु प। साइटा म नयस देखू।"},{"i":311338,"h":"Zink","b":"[n.] ; जक देखू।"},{"i":311339,"h":"Zinkenite","b":"[n.] ; इ पात-धूसर धा वक ख नज, ए टमनी आ सीसाक स फाइड।"},{"i":311340,"h":"Zinky","b":"[a.] ; जक क देखू।"},{"i":311341,"h":"Zinnia","b":"[n.] ; क पो जट जा त ज नयाक कोनो पादप, मे सकोक जड़ -बूटी जा हमे वपर त प ी आ बड़का रंगीन फ ू ल होइत छैक। ज नया ए लगे स खेतीमे सवा धक सामा य जा त अ छ।"},{"i":311342,"h":"Zinnwaldite","b":"[n.] ; ल थयमयु त एकटा कारक अ क, ायः टन-अय कसँ संयु त।"},{"i":311343,"h":"Zinsang","b":"[n.] ; डलुंडुंग।"},{"i":311344,"h":"Zinziberaceous","b":"[a.] ; ज जबेरे सयसक समान।"},{"i":311345,"h":"Zion","b":"[n.] ; अतः, ई रतं , वा ई रक कली सया।"},{"i":311346,"h":"Zion","b":"[n.] ; य शलेममे एकटा पहाड़ , जे इ ाए लया ारा ओ नगरक जीतलाक बाद दाऊद आ नकर उ रा धकार क राजक य नवास बनल।"},{"i":311347,"h":"Zion","b":"[n.] ; वग य य शलेम; वग।"},{"i":311348,"h":"Zip","b":"[adv.] ; जपसँ ब द क े नाइ"},{"i":311349,"h":"zip","b":"[n.] ; जीप"},{"i":311350,"h":"zip","b":"[noun] ; ज़प (फा टनर)"},{"i":311351,"h":"Zip","b":"[v] ; सङ ् कचत करब, संवृण करब"},{"i":311352,"h":"ZIP code","b":"ज़प कोड (डाक)"},{"i":311353,"h":"Zip ﬁle","b":"[n] ; संवृतस का, सङ ् कचत स का"},{"i":311354,"h":"zip-code","b":"[n.] ; लाक सं या"},{"i":311355,"h":"Ziphioid","b":"[n.] ; ज फऑइड देखू।"},{"i":311356,"h":"zipper","b":"[noun] ; ज़प / चेन"},{"i":311357,"h":"Zirco-","b":"एकटा संयोजन प ( वशेषण पमे सेहो यु त) जे जका नयमक क तपय गुण यौ गकक त वक पमे दशबैत अ छ।"},{"i":311358,"h":"Zircoﬂuoride","b":"[n.] ; जका नयम आ हाइ ोजन, वा कोनो अ य धना मक त व वा मूलकक गुण लोराइड।"},{"i":311359,"h":"Zircon","b":"[n.] ; चतु कोणीय टलमे पाओल जायवाला एकटा ख नज, सामा यतः भूरा वा धूसर रंगक। ए हमे स लका आ जका नया होइत छैक। लाल क , जे र नक पमे यु त होइत अ छ, हाय स थ कहल जाइत अ छ। सीलोनसँ रंगहीन, ह का-पीला वा धुआँधार-भूरा क क जागन कहल जाइत अ छ।"},{"i":311360,"h":"Zircona","b":"[n.] ; जका नया।"},{"i":311361,"h":"Zirconate","b":"[n.] ; जका नक अ लक एकटा लवण।"},{"i":311362,"h":"Zirconia","b":"[n.] ; जका नयमक ऑ साइड, जे ेत चूणक पमे ा त होइत अ छ आ ए हमे अ लीय आ ार य नू गुण होइत छैक। अपनी अदा ता आ त त होयपर खर काशक कारण एकरा ममंड- काशक लाठ मे मलायल जाइत अ छ।"},{"i":311363,"h":"Zirconic","b":"[a.] ; जका नयमसँ संबं धत, ओकर यु त, वा ओकर समान।"},{"i":311364,"h":"Zirconium","b":"[n.] ; एक कारक धातु"},{"i":311365,"h":"Zirconium","b":"[n.] ; काबन- स लकन वगक एकटा लभ त व, धातु आ अधातुक बीचक, जकन ख नजसँ काला काजल-समान चूण वा धूसर धा वक टलीय पदाथक पमे ा त। तीक Zr। परमाण भार ९०.४।"},{"i":311366,"h":"Zircono","b":"जका- देखू।"},{"i":311367,"h":"Zirconoid","b":"[n.] ; भाग आठ-कोणीय परा मड, एकटा प जे चतु कोणीय टलमे सामा य अ छ — ए ह पसँ कहल जाइत अ छ कारण ई प जकन टलमे ायः पाओल जाइत अ छ।"},{"i":311368,"h":"Zither","b":"[n.] ; ऑ या आ जमनीमे यु त एकटा संगीत वा यं । ए हमे तीस सँ चालीस तार एकटा उथला व न-बोडपर लगायल होइत अ छ, जे कलाकारक सामने टेबलपर ै तज पसँ रखल रहैत अ छ, जे नू हाथसँ बजबैत अ छ।"},{"i":311369,"h":"Zither","b":"[n.] ; सतार"},{"i":311370,"h":"Zittern","b":"[n.] ; सटन देखू।"},{"i":311371,"h":"Zizania","b":"[n.] ; भारतीय चाउर स हत घासक एकटा जा त। चाउरक अ तगत भारतीय चाउर देखू।"},{"i":311372,"h":"Zizel","b":"[n.] ; सु लक।"},{"i":311373,"h":"zling","b":"[adj.] ; अकला मक"},{"i":311374,"h":"zn. aﬃliation","b":"[n.] ; स ब न"},{"i":311375,"h":"zn. real name","b":"[n.] ; खास नाम"},{"i":311376,"h":"Zn. stoppage","b":"[n.] ; अड़ाँची"},{"i":311377,"h":"Zoa","b":"[pl.] ; जूनक"},{"i":311378,"h":"Zoanthacea","b":"[n. pl.] ; ए टना रयाक एकटा उपवग, जा हमे जोए थस आ संबं धत जा त शा मल अ छ, जे थायी पसँ अपन आधारसँ जुड़ल होइत अ छ।"},{"i":311379,"h":"Zoantharia","b":"[n. pl.] ; ए थोजोआक समान।"},{"i":311380,"h":"Zoantharian","b":"[a.] ; जोए थे रयासँ संबं धत वा ओकर अनु प।"},{"i":311381,"h":"Zoantharian","b":"[n.] ; ए थोजोआमेसँ एकटा।"},{"i":311382,"h":"Zoanthodeme","b":"[n.] ; एकटा संयु त ए थोजोआनक जूऑइड, सामू हक पमे।"},{"i":311383,"h":"Zoanthoid","b":"[a.] ; जोए थे सयासँ संबं धत वा ओकर अनु प।"},{"i":311384,"h":"Zoanthropy","b":"[n.] ; एकटा कारक मनो ंश जा हमे रोगी वयंक नचला जंतुमेसँ एकटामे पा त रत मानैत अ छ।"},{"i":311385,"h":"Zoanthus","b":"[n.] ; ए टना रयाक एकटा जा त, जा हमे अनेक जा त शा मल अ छ, अ धकतर उ णक टबंधीय समु मे पाओल जाइत अ छ। जूऑइड वा पॉ लप छोट, ल बाकार ए ट नयाक समान होइत अ छ जे अपन आधारमे मांसल टोलनसँ एक संग जुड़ल रहैत अ छ।"},{"i":311386,"h":"Zobo","b":"[n.] ; ए शयामे माँस आ धक लेल पालल जायवाला एकटा कारक घरेलू पशु। एकरा जेबू आ याकक संकर मानल जाइत अ छ।"},{"i":311387,"h":"Zocco","b":"[n.] ; जोकोलोक अ य प"},{"i":311388,"h":"Zoccolo","b":"[n.] ; सॉकलक समान।"},{"i":311389,"h":"Zocle","b":"[n.] ; सॉकलक समान।"},{"i":311390,"h":"Zodiac","b":"[adj.] ; रा शक च"},{"i":311391,"h":"Zodiac","b":"[n.] ; आकाशमे एकटा का प नक प ी, १६-१८ ड ी चौड़ा, जा हक म यमे ां तवृ वा सूयक पथ अ छ। ए हमे बारह न -समूह अ छ जा हसँ रा श-च क बारह रा शक नामकरण भेल।"},{"i":311392,"h":"Zodiac","b":"[n.] ; एकटा करधनी; एकटा प ा।"},{"i":311393,"h":"Zodiac","b":"[n.] ; रा श-च / भच"},{"i":311394,"h":"Zodiac","b":"[n.] ; रा श-च क च , तीक, आ न - समूहक दशबायवाला आक ृ त।"},{"i":311395,"h":"Zodiacal","b":"[a.] ; रा श-च सँ संबं धत वा ओकर अनु प; रा श-च क भीतर थत।"},{"i":311396,"h":"Zodiacal","b":"[adj.] ; रा शक च सँ स ब धी"},{"i":311397,"h":"Zoea","b":"[n.] ; क तपय दशपाद टे शया, वशेषतः े कड़ा आ क तपय एनोमुराक एकटा वशेष लावा-अव था।"},{"i":311398,"h":"Zoetrope","b":"[n.] ; एकटा काशीय खलौना जा हमे एकटा बेलनक भीतर भागपर घुमयवाला आक ृ त, ओकर प र धमे दरारसँ देखलापर एकटा एकल आक ृ तक पमे देखाइत अ छ जे वाभा वक ग त व धक मसँ गुजरैत अ छ।"},{"i":311399,"h":"Zohar","b":"[n.] ; एकटा य दी रह यवादी ंथ जे परंपरागत पसँ र बी साइमन बेन योचीक ेय देल जाइत अ छ। आधु नक समालोचक एकरा १३व शता दीक संकलन मानैत अ छ।"},{"i":311400,"h":"Zoic","b":"[a.] ; जंतुसँ, वा जंतु-जीवनसँ, संबं धत।"},{"i":311401,"h":"Zoide","b":"[n.] ; मेर ड देखू।"},{"i":311402,"h":"Zoilean","b":"[a.] ; जोइलसक वशेषता यु त, एकटा कटु, ई यालु, अ यायपूण आलोचक जे ईसासँ लगभग २७० वष प हने जी वत छलाह।"},{"i":311403,"h":"Zoilism","b":"[n.] ; शैली वा ढंगमे जोइलसक समानता; दोष ढूँढ़यवाला आलोचना; नदा।"},{"i":311404,"h":"Zoisite","b":"[n.] ; एकटा धूसर वा सफ े दाहट ख नज जे ऑथारो बक, मीय टलमे पाओल जाइत अ छ। ई ए ु मना आ चूनाक स लक े ट अ छ आ ए पडोटसँ मलैत- जुलैत अ छ।"},{"i":311405,"h":"Zokor","b":"[n.] ; एकटा ए शयाई बल खनयवाला क ृं तक ( सफ नयस ए पालै स) जे छछूंदर-चूहासँ मलैत-जुलैत अ छ। ई अ ाई पवतमालाक मूल नवासी अ छ।"},{"i":311406,"h":"Zollverein","b":"[n.] ; शा दक पमे, सीमा-शु क संघ; वशेष पसँ, शयाक नेतृ वमे क तपय जमन रा यक बीच मशः बनल सीमा-शु क संघपर लागू।"},{"i":311407,"h":"zombie","b":"[noun] ; ज़ाबी (का प नक)"},{"i":311408,"h":"zombie","b":"[noun] ; मूख (बेवक ू फ)"},{"i":311409,"h":"Zomboruk","b":"[n.] ; जु बू क देखू।"},{"i":311410,"h":"Zon laboratory","b":"योगशाला"},{"i":311411,"h":"Zona","b":"[n.] ; एकटा े वा प ी; एकटा परत।"},{"i":311412,"h":"Zonae","b":"[pl.] ; जोनाक"},{"i":311413,"h":"Zonal","b":"[a.] ; एकटा े सँ संबं धत वा ओकर अनु प; े वा े सभक पमे।"},{"i":311414,"h":"zonal","b":"[adj.] ; अ लीय"},{"i":311415,"h":"zonal","b":"[n.] ; अ लीय"},{"i":311416,"h":"zonal on","b":"[adj.] ; अड् चलीय"},{"i":311417,"h":"Zonar","b":"[n.] ; एकटा करधनी जे लेवे टक ईसाई आ य दीक मुसलमानसँ भ न दशाबय लेल प हरय पड़ैत छल न।"},{"i":311418,"h":"Zonaria","b":"[n. pl.] ; तनपायी जंतुक एकटा वभाग जा हमे अपरा े ब होइत अ छ।"},{"i":311419,"h":"Zonate","b":"[a.] ; समांतर तलसँ वभा जत; जेना जोनेट टे ा पोर, जे क तपय लाल शैवालमे पाओल जाइत अ छ।"},{"i":311420,"h":"Zone","b":"[n.] ; अ ांश आ तापमानक संदभमे पृ वीक पाँच महान वभागमेसँ एकटा।"},{"i":311421,"h":"zone","b":"[n.] ; अ ल"},{"i":311422,"h":"Zone","b":"[n.] ; एकटा करधनी; एकटा घेरा।"},{"i":311423,"h":"Zone","b":"[n.] ; कसी व तुक चा कात फ ै लल एकटा प ी वा धार ।"},{"i":311424,"h":"Zone","b":"[n.] ; कसी व तुक चा कात वृ क एकटा प ी वा े ; जेना पहाड़पर सदाह रत वृ क े ।"},{"i":311425,"h":"Zone","b":"[n.] ; े / क टब ध / म डल / इलाका"},{"i":311426,"h":"zone","b":"[n.] ; डन"},{"i":311427,"h":"Zone","b":"[n.] ; समांतर तलक बीचक गोलाक सतहक भाग; अ क ल बवत् तलक बीच ां त-सतहक भाग।"},{"i":311428,"h":"Zone","b":"[n.] ; पर पर समांतर त ेदन रेखावाला तलक म।"},{"i":311429,"h":"Zone","b":"[n.] ; प र ध; घेरा।"},{"i":311430,"h":"zone","b":"[n.] ; म डल"},{"i":311431,"h":"Zone","b":"[n.] ; मेखला"},{"i":311432,"h":"zone","b":"[noun] ; े (भाग)"},{"i":311433,"h":"Zone","b":"[v. t.] ; करधनी बा हब; चा कात घेरब।"},{"i":311434,"h":"zone of peace","b":"[n.] ; शा त े"},{"i":311435,"h":"Zoned","b":"[a.] ; े वा करधनी प हरयवाला।"},{"i":311436,"h":"Zoned","b":"[a.] ; े वा संक े ी प ी यु त; धार दार।"},{"i":311437,"h":"Zoned","b":"[a.] ; जोनेट।"},{"i":311438,"h":"Zoneless","b":"[a.] ; े र हत; बना करधनीक।"},{"i":311439,"h":"Zonnar","b":"[n.] ; जोनार देखू।"},{"i":311440,"h":"Zonular","b":"[a.] ; एकटा े सँ संबं धत वा ओकर अनु प; े -आक ृ त।"},{"i":311441,"h":"Zonule","b":"[n.] ; एकटा छोट े वा करधनी।"},{"i":311442,"h":"Zonulet","b":"[n.] ; एकटा जोनूल।"},{"i":311443,"h":"Zonure","b":"[n.] ; द ण अ काक जोनुरा जा तक कई छपकलीमेसँ कोनो एकटा, जे पथर ला थानमे सामा यतः पाओल जाइत अ छ।"},{"i":311444,"h":"zoo","b":"[n.] ; च ड़याखाना"},{"i":311445,"h":"Zoo","b":"[n.] ; पशुक वा टका"},{"i":311446,"h":"zoo","b":"[noun] ; च ड़याघर (सं हालय)"},{"i":311447,"h":"Zoo-","b":"ीक श द 'जूऑन' (जंतु) सँ बनल संयोजन- प, जेना जूजे नक, जूलॉजी आ दमे।"},{"i":311448,"h":"Zoochemical","b":"[a.] ; जूरसायनसँ संबं धत।"},{"i":311449,"h":"Zoochemistry","b":"[n.] ; जंतु-रसायन; वशेषतः, जंतु- शर रक संरचनामे वेश करयवाला रासाय नक यौ गकक वणन, जीव-रसायनसँ भ न।"},{"i":311450,"h":"Zoochemy","b":"[n.] ; जंतु-रसायन; जूक े म ी।"},{"i":311451,"h":"Zoochlorella","b":"[n.] ; क तपय टटर, हाइ ा, आ अ य अकशे क क भीतर पाओल जायवाला छोट ह रयर कणाकार शर रमेसँ एकटा।"},{"i":311452,"h":"Zoocyst","b":"[n.] ; क तपय ोटोजोआ आ एकको शक य पादप ारा बनायल एकटा पुटी जा हमे अ तव तु बड़ सं यामे क णकाओमे वभा जत होइत अ छ, जेकरामेसँ येक एकटा क टाण बनैत अ छ।"},{"i":311453,"h":"Zoocytia","b":"[pl.] ; जूसाइ टयमक"},{"i":311454,"h":"Zoocytium","b":"[n.] ; क तपय सामा जक इ यूसो रयाक सामा य आधार, ायः शाखायु त।"},{"i":311455,"h":"Zoodendria","b":"[pl.] ; जूडे यमक"},{"i":311456,"h":"Zoodendrium","b":"[n.] ; क तपय इ यूसो रयाक उप नवेशक शाखायु त, आ ायः वृ ाकार, आधार।"},{"i":311457,"h":"Zooecia","b":"[pl.] ; जूइ शयमक"},{"i":311458,"h":"Zooecium","b":"[n.] ; ायोजोआक संवेदनशील जूऑइडक घेरय वाला को शका वा नलीमेसँ एकटा। समु ी काई (Sea Moss)क च देखू।"},{"i":311459,"h":"Zooerythrine","b":"[n.] ; व भ न प ीक पंखमे पाओल जायवाला एकटा व च काब नक लाल रंग-पदाथ।"},{"i":311460,"h":"Zoogamous","b":"[a.] ; जूगैमीसँ संबं धत वा ओकर अनु प।"},{"i":311461,"h":"Zoogamy","b":"[n.] ; जंतुक ल गक जनन।"},{"i":311462,"h":"Zoogenic","b":"[a.] ; जूजेनी, पशु-उ पादनसँ संबं धत वा ओकर अनु प।"},{"i":311463,"h":"Zoogeny","b":"[n.] ; जूगोनीक अ य प"},{"i":311464,"h":"Zoogeographical","b":"[a.] ; जू ाफ सँ संबं धत वा ओकर अनु प।"},{"i":311465,"h":"Zoogeography","b":"[n.] ; जंतुक भौगो लक वतरणक अ ययन वा वणन।"},{"i":311466,"h":"Zoogloea","b":"[n.] ; एकटा चप चपा जले टनस पदाथमे समा हत जीवाणक उप नवेश वा समूह। जू लोआ ती ग तसँ बढ़ैत जीवाणक वकासक ममे आयवाला एकटा णक अव थाक वशेषता अ छ। वशेषण पमे सेहो यु त।"},{"i":311467,"h":"Zoogony","b":"[n.] ; जी वत ाणीक नमाणक स ा त।"},{"i":311468,"h":"Zoographer","b":"[n.] ; जंतुक, नकर प-आक ृ त आ आदतक, वणन करयवाला त।"},{"i":311469,"h":"Zoographic","b":"[a.] ; जू ा फकलक अ य प"},{"i":311470,"h":"Zoographical","b":"[a.] ; जंतुक वणनसँ संबं धत वा ओकर अनु प।"},{"i":311471,"h":"Zoographist","b":"[n.] ; एकटा जू ाफर।"},{"i":311472,"h":"Zoography","b":"[n.] ; जंतुक, नकर प-आक ृ त आ आदतक, वणन।"},{"i":311473,"h":"Zooid","b":"[a.] ; जंतुसँ संबं धत वा ओकर समान।"},{"i":311474,"h":"Zooid","b":"[n.] ; एकटा काब नक शर र वा को शका जेकरामे ग तशीलता होइत छैक, जेना शु ाण को शका वा शु ाण-जूऑइड।"},{"i":311475,"h":"Zooid","b":"[n.] ; वकासक न न अव थामे एकटा जंतु, जेना एका तर पीढ़ मे म यवत पमेसँ एकटा।"},{"i":311476,"h":"Zooid","b":"[n.] ; संयु त समूहक तगत जंतुमेसँ एकटा, जेना ए थोजोआ, हाइ ॉइ डआ, आ ायोजोआ; — कखनो-काल ओहन तमे सी मत जा हमे मुँह आ पाचन- अंग वक सत न ह होइत छैक।"},{"i":311477,"h":"Zooidal","b":"[a.] ; जूऑइडसँ संबं धत वा ओकर अनु प; जेना, जूऑइडल प।"},{"i":311478,"h":"Zoolatry","b":"[n.] ; जंतुक पूजा।"},{"i":311479,"h":"zoolatry","b":"[n.] ; ड् ग"},{"i":311480,"h":"zoolatry","b":"[n.] ; पं ली"},{"i":311481,"h":"zoolatry","b":"[n.] ; पशुपूजा"},{"i":311482,"h":"Zoologer","b":"[n.] ; एकटा ाणी- व ानी।"},{"i":311483,"h":"Zoological","b":"[a.] ; ाणी- व ानसँ, वा जंतु- व ानसँ, संबं धत वा ओकर अनु प।"},{"i":311484,"h":"zoological","b":"[adj.] ; ा ण (जीव)"},{"i":311485,"h":"Zoological","b":"[adj.] ; ाणी व ासँ स ब धी"},{"i":311486,"h":"Zoologically","b":"[adv.] ; ाणी-वै ा नक ढंगसँ; ाणी- व ानक स ा त अनुसार।"},{"i":311487,"h":"Zoologies","b":"[pl.] ; ाणी- व ानक"},{"i":311488,"h":"Zoologist","b":"[n.] ; ाणी- व ानमे द त।"},{"i":311489,"h":"Zoology","b":"[n.] ; ए ह व ानपर एकटा ंथ।"},{"i":311490,"h":"Zoology","b":"[n.] ; जीव- व ानक ओ भाग जे जंतु- जगतसँ संबं धत अ छ, जा हमे सभ जी वत आ वलु त जंतुक संरचना, ूण व ान, वकास, वग करण, आदत, आ वतरण शा मल अ छ।"},{"i":311491,"h":"zoology","b":"[n.] ; जीव व ान"},{"i":311492,"h":"Zoology","b":"[n.] ; ा ण व ान / जीवशा"},{"i":311493,"h":"Zoology","b":"[n.] ; ा ण व ान"},{"i":311494,"h":"zoology","b":"[noun] ; ा ण व ान (शा )"},{"i":311495,"h":"Zoom","b":"[n] ; सपक, उपसपण- अपसपण"},{"i":311496,"h":"Zoom","b":"[v.] ; हवाइ जहाजक खड़ा बल ऊपर चढ़ए लेल जोर लगेनाइ"},{"i":311497,"h":"zoom","b":"[verb] ; तेज बढ़ब (ग त)"},{"i":311498,"h":"Zoom In","b":"[n] ; आकार प रवतन, जूम"},{"i":311499,"h":"Zoom In","b":"[n] ; उपसपण, उपसपण"},{"i":311500,"h":"Zoom In","b":"[n] ; पैघ कर, जूम इन"},{"i":311501,"h":"zoom lens","b":"[noun] ; ज़ूम लस (क ै मरा)"},{"i":311502,"h":"Zoom Out","b":"[n] ; अपसपण, अपसपण"},{"i":311503,"h":"Zoom Out","b":"[n] ; छोट कर, जूम आउट"},{"i":311504,"h":"Zoomelanin","b":"[n.] ; अनेक प ीक पंखक काला रंग देयवाला एकटा रंजक।"},{"i":311505,"h":"Zoomorphic","b":"[a.] ; जूमॉ फ मसँ संबं धत वा ओकर अनु प।"},{"i":311506,"h":"Zoomorphism","b":"[n.] ; ई र वा देवताक नचला जंतुक पमे, वा नकर गुणक संग, त न ध व।"},{"i":311507,"h":"Zoomorphism","b":"[n.] ; जंतु- पक त न ध व वा उपयोगक गुण; जेना, अलंकरणमे जूमॉ फ म।"},{"i":311508,"h":"Zoomorphism","b":"[n.] ; मनु यक जंतुमे पांतरण।"},{"i":311509,"h":"Zoon","b":"[n.] ; एकटा जंतु जे एकमा अंडाक उ पाद अ छ; — जूऑइडक वपर त।"},{"i":311510,"h":"Zoon","b":"[n.] ; एकटा संयु त जंतुक पूण वक सत तमेसँ कोनो एकटा।"},{"i":311511,"h":"Zoonic","b":"[a.] ; जंतुसँ संबं धत; जंतु-पदाथसँ ा त।"},{"i":311512,"h":"Zoonite","b":"[n.] ; कोनो खं डत जंतुक सै ा तक अनु थ वभाजनमेसँ एकटा।"},{"i":311513,"h":"Zoonite","b":"[n.] ; सं धपाद जंतुक शर रक खंडमेसँ एकटा।"},{"i":311514,"h":"Zoonomy","b":"[n.] ; जंतु-जीवनक नयम, वा ओ व ान जे जंतु-जीवनक प रघटना, नकर कारण आ संबंधक वचार करैत अ छ।"},{"i":311515,"h":"Zoonule","b":"[n.] ; जूनाइटक समान।"},{"i":311516,"h":"Zoopathology","b":"[n.] ; जंतु-रोग व ान।"},{"i":311517,"h":"Zoophaga","b":"[n. pl.] ; व भ न मांसाहार आ क टभ ी जंतुक समेटयवाला एकटा क ृ म समूह।"},{"i":311518,"h":"Zoophagan","b":"[n.] ; एकटा जंतु जे जांतव आहारपर जी वत रहैत अ छ।"},{"i":311519,"h":"Zoophagous","b":"[a.] ; जंतुपर भोजन करयवाला।"},{"i":311520,"h":"Zoophilist","b":"[n.] ; जंतुक ेमी।"},{"i":311521,"h":"Zoophily","b":"[n.] ; जंतुसँ ेम।"},{"i":311522,"h":"Zoophite","b":"[n.] ; एकटा जूफाइट।"},{"i":311523,"h":"Zoophoric","b":"[a.] ; जंतुक आक ृ त धारण करयवाला वा ओकर आधार तंभक पमे; जेना, एकटा जूफो रक तंभ।"},{"i":311524,"h":"Zoophorous","b":"[n.] ; आ क ेव आ कॉ नसक बीचक भाग; भ प ी ( ज); — ए हपर जंतुक आक ृ त उक े रल रहैत छैक त ए ह नामसँ जानल जाइत अ छ।"},{"i":311525,"h":"Zoophyta","b":"[n. pl.] ; जंतुक एकटा ापक क ृ म आ वषम समूह, जे प हने कई ाणी- व ानी वीकार करैत छलाह। ए हमे सीलटरेट, एकाइनोडम, पंज, ायोजोआ, ोटोजोआ आ द शा मल छल।"},{"i":311526,"h":"Zoophyte","b":"[n.] ; ज तु आ उद भद नूक गुण राखए बला त व"},{"i":311527,"h":"Zoophyte","b":"[v. i.] ; अकशे क जंतुक अनेक जा तमेसँ कोनो एकटा जे देखावटमे वा वकास-शैलीमे पादपसँ कम-बेसी मलैत-जुलैत अ छ, जेना वाल, गॉगा नयन, समु ी एनीमोन, हाइ ॉइड, ायोजोअन, पंज आ द; वशेष पसँ ओ जे शाखायु त वा वृ ाकार पक संयु त उप नवेश बनबैत अ छ।"},{"i":311528,"h":"Zoophyte","b":"[v. i.] ; जूफाइटामेसँ कोनो एकटा।"},{"i":311529,"h":"Zoophytic","b":"[a.] ; जूफाइ टकलक अ य प"},{"i":311530,"h":"Zoophytical","b":"[a.] ; जूफाइटसँ संबं धत वा ओकर अनु प।"},{"i":311531,"h":"Zoophytoid","b":"[a.] ; जूफाइटसँ संबं धत वा ओकर समान।"},{"i":311532,"h":"Zoophytological","b":"[a.] ; जूफाइटोलॉजीसँ संबं धत वा ओकर अनु प।"},{"i":311533,"h":"Zoophytology","b":"[n.] ; जूफाइटसभक ाक ृ तक इ तहास।"},{"i":311534,"h":"Zoopraxiscope","b":"[n.] ; फ े ना क टो कोपसँ मलैत- जुलैत वा ओ हसँ समान एकटा यं जा ह ारा परदापर े पत च जंतुक वाभा वक ग त व ध आ द द शत करैत अ छ।"},{"i":311535,"h":"Zoopsychology","b":"[n.] ; जंतु-मनो व ान।"},{"i":311536,"h":"Zoosperm","b":"[n.] ; शु ाण कणमेसँ एकटा; शु ाण- जूऑइड।"},{"i":311537,"h":"Zoosporangium","b":"[n.] ; एकटा बीजाण, वा जू पोर यु त धारक।"},{"i":311538,"h":"Zoospore","b":"[n.] ; एक वा अ धक पतला प माभसँ यु त बीजाण, जा हक क ं पनसँ ई पा नमे तैरैत अ छ। जू पोर अनेक ह रयर आ कछु जैतुनी-भूरा शैवालमे उ प न होइत अ छ। क तपय जा तमे एकरा बृहत् मै ोजू पोर आ लघु माइ ोजू पोरमे वभा जत कयल जाइत अ छ। पोरोजूऑइड आ वाम पोर सेहो कहल जाइत अ छ।"},{"i":311539,"h":"Zoospore","b":"[n.] ; वाम पोर देखू।"},{"i":311540,"h":"Zoosporic","b":"[a.] ; जू पोरसँ संबं धत वा ओकर ृ तक।"},{"i":311541,"h":"Zootic","b":"[a.] ; संग ठत शर रक अवशेष यु त; — शैल वा म ीक संदभमे कहल जाइत अ छ।"},{"i":311542,"h":"Zootomical","b":"[a.] ; जूटोमीसँ संबं धत वा ओकर अनु प।"},{"i":311543,"h":"Zootomist","b":"[n.] ; जंतुक व ेदन करयवाला, वा जूटोमीमे द , त।"},{"i":311544,"h":"Zootomy","b":"[n.] ; जंतुक व ेदन वा शार रक संरचना — ए ोटोमीसँ भ न।"},{"i":311545,"h":"Zootrophic","b":"[a.] ; जंतुक पोषणसँ संबं धत वा ओकर अनु प।"},{"i":311546,"h":"Zoozoo","b":"[n.] ; जंगली कबूतर।"},{"i":311547,"h":"Zope","b":"[n.] ; एकटा यूरोपीय मीठा पा नक ीम (अ ा मस बेलेरस)।"},{"i":311548,"h":"Zopilote","b":"[n.] ; उ बू, वा अमे रक काला ग ।"},{"i":311549,"h":"Zoril","b":"[n.] ; जो रलाक समान।"},{"i":311550,"h":"Zorilla","b":"[n.] ; इ टो न स जा तक लघु अ क मांसाहार जंतुमेसँ कोनो एकटा जे नेवला आ क ं कसँ संबं धत अ छ।"},{"i":311551,"h":"Zoroaster","b":"[noun] ; जरथु (पैगंबर)"},{"i":311552,"h":"Zoroastrian","b":"[a.] ; जरथु , वा नकर धा मक णालीसँ, संबं धत वा ओकर अनु प।"},{"i":311553,"h":"Zoroastrian","b":"[n.] ; जरथु क अनुयायी; जे जरथु वादक मा यता देइत अ छ।"},{"i":311554,"h":"Zoroastrian","b":"[noun] ; जरथु धम ( त)"},{"i":311555,"h":"Zoroastrianism","b":"[n.] ; ाचीन फारसीक वधायक आ नबी जरथु क धा मक णाली, जे फारसक रा ीय आ था छल; म देइ म। ए ह णालीमे एकटा शुभ आ मा (ओमु द) आ एकटा वरोधी आ मा (अह रमन) क पत अ छ। तुलना क अ न-पूजासँ।"},{"i":311556,"h":"Zoroastrianism","b":"[noun] ; जरथु धम (पारसी)"},{"i":311557,"h":"Zoroastrism","b":"[n.] ; जरथु वादक समान।"},{"i":311558,"h":"Zoster","b":"[n.] ; दाद ( शग स)।"},{"i":311559,"h":"Zostera","b":"[n.] ; नाइडेसी वा पाडवीड प रवारक पादपक एकटा जा त। जो टेरा मर ना सामा यतः समु ी घास आ ईल ास नामसँ जानल जाइत अ छ।"},{"i":311560,"h":"Zosterops","b":"[n.] ; प ीक एकटा जा त जे ेत-ने ( हाइट-आई) प ीक समेटैत अ छ। हाइट-आई देखू।"},{"i":311561,"h":"Zouave","b":"[n.] ; अतः एकटा सै नक दलक एकटा सद य जे जूआव पोशाक आ अ यास अपनबैत अ छ, जेना संयु त रा य अमे रकाक गृहयु (१८६१-६५) मे कई वयंसेवी रे जमट कयलक।"},{"i":311562,"h":"Zouave","b":"[n.] ; च सेनामे एकटा स य आ कठोर सै नक दलक एकटा सद य, मूलतः अरब, मुदा आब चमेन जे अरब पोशाक प हरैत अ छ।"},{"i":311563,"h":"Zounds","b":"[interj.] ; प हने शपथक पमे आ ोध वा आ यक अ भ तक पमे यु त एकटा उ ार।"},{"i":311564,"h":"Zoutch","b":"[v. t.] ; भाप वा तरलसँ पकायब, जेना लाउं डर, सप-मीन आ दक, क े वल ढक ै त भर वक संग।"},{"i":311565,"h":"Zu/is","b":"[n. pl.] ; पुए लो इं डयनक एकटा जनजा त जे यू मे सकोमे जुनी नदीपर एकटा गाममे बसैत अ छ।"},{"i":311566,"h":"Zubr","b":"[n.] ; औरो स।"},{"i":311567,"h":"zucchini","b":"[noun] ; तोरई (जु कनी)"},{"i":311568,"h":"zucchini","b":"[noun] ; तोरई (स जी)"},{"i":311569,"h":"Zuche","b":"[n.] ; एकटा गाछक ठूँ ठ।"},{"i":311570,"h":"Zuchetto","b":"[n.] ; टासर ढकयवाला खोपड़ -टोपी, बेरेटाक नीचाँ प हरल जाइत अ छ। पोपक सफ े द; का डनलक लाल; बशपक बगनी; पादर क काला।"},{"i":311571,"h":"Zufolo","b":"[n.] ; एकटा छोट बाँसुर वा लै जयोलेट, वशेषतः ओ जे प ीक सखाबय लेल यु त होइत अ छ।"},{"i":311572,"h":"Zuisin","b":"[n.] ; अमे रक वडजन।"},{"i":311573,"h":"Zulus","b":"[n. pl.] ; का फर जा तसँ संबं धत सवा धक मह वपूण जनजा त। एकरा लोक अ काक द ण-पूव तटपर बसैत अ छ, मुदा प हने अ धक व तृत देशपर अ धकार रहैक। यु - यता, साहस, आ सै नक क ु शलताक लेल स ।"},{"i":311574,"h":"Zumbooruk","b":"[n.] ; ऊ ँ टक पीठपर था पत घूमयवाला आधारपर टकल एकटा छोट तोप, जा हसँ गोली दागल जाइत अ छ — पूवमे यु त।"},{"i":311575,"h":"Zumic","b":"[n.] ; जुमोमीटरक अ य प"},{"i":311576,"h":"Zumological","b":"[n.] ; जुमोमीटरक अ य प"},{"i":311577,"h":"Zumology","b":"[n.] ; जुमोमीटरक अ य प"},{"i":311578,"h":"Zumometer","b":"[n.] ; जाइ मक, जाइमोलॉ जकल आ द देखू।"},{"i":311579,"h":"Zunyite","b":"[n.] ; कोलोराडोमे जुनी खानमे चतु फलक य टलमे पाओल जायवाला ए ु मनाक एकटा लूओ स लक े ट।"},{"i":311580,"h":"Zwanziger","b":"[n.] ; एकटा ऑ याई चाँदीक स का जे २० ॉय जर वा लगभग १० सटक बराबर होइत अ छ।"},{"i":311581,"h":"Zygantra","b":"[pl.] ; जाइगै मक"},{"i":311582,"h":"Zygantrum","b":"[n.] ; जाइगो फ नक अ तगत देखू।"},{"i":311583,"h":"Zygapophyses","b":"[pl.] ; जाइगैपो फ ससक"},{"i":311584,"h":"Zygapophysis","b":"[n.] ; कशे काक सं ध- वधनमेसँ एकटा, जा हमे सामा यतः चा रटा होइत छैक — अ गला आ पा छला। कशे काक अ तगत देखू।"},{"i":311585,"h":"Zygenid","b":"[n.] ; जाइगे नड प रवारक अनेक जा तमेसँ एकटा शलभ, जा हमे अ धकतर चमक ला रंगक होइत छैक। का -पर आ वेल वनपालक उदाहरण छ थ। वशेषण पमे सेहो यु त।"},{"i":311586,"h":"Zygobranchia","b":"[n. pl.] ; समु ी उदरपाद मोल कक एकटा वभाग जा हमे शर रक नू दस लोम वक सत होइत छैक आ वृ क-अंग सेहो युगलमे होइत छैक। अबलोन (है लयो टस) आ क होल ल पेट ( फसुरेला) एकर उदाहरण छ थ।"},{"i":311587,"h":"Zygobranchiate","b":"[a.] ; जाइगो कयासँ संबं धत वा ओकरा अनु प।"},{"i":311588,"h":"Zygodactyl","b":"[n.] ; जाइगोडै टाइलक अ य प"},{"i":311589,"h":"Zygodactylae","b":"[n. pl.] ; जाइगोडै टाइल प ी। सी मत अथमे एकटा प ी- वभागपर लागू जा हमे दा ढ़मा- प ी, टूकान, मधु-मागदशक आ अ य संबं धत प ी शा मल छ थ।"},{"i":311590,"h":"Zygodactyle","b":"[n.] ; कोनो जाइगोडै टाइल प ी।"},{"i":311591,"h":"Zygodactyli","b":"[n. pl.] ; क ै सोरेसक समान।"},{"i":311592,"h":"Zygodactylic","b":"[a.] ; जाइगोडै टाइलसक अ य प"},{"i":311593,"h":"Zygodactylous","b":"[a.] ; जोड़ा-पैरयु त; अंगु ल युगलमे था पत — एहन प ीपर लागू जा हमे आगू आ पाछू अंगु ल होइत छैक, जेना तोता, कोयल, कठफोड़वा आ द।"},{"i":311594,"h":"Zygoma","b":"[n.] ; जुगल, मेलर वा गाल-ह ।"},{"i":311595,"h":"Zygoma","b":"[n.] ; टे पोरल ह क जाइगोमै टक वधन।"},{"i":311596,"h":"Zygoma","b":"[n.] ; संपूण जाइगोमै टक चाप।"},{"i":311597,"h":"Zygomatic","b":"[a.] ; जाइगोमाक, ओकरासँ संबं धत वा ओकर े मे।"},{"i":311598,"h":"Zygomorphic","b":"[a.] ; जाइगोमॉफसक अ य प"},{"i":311599,"h":"Zygomorphous","b":"[a.] ; पा य पसँ सम मत — जीव वा जीवक अंशपर कहल जाइत अ छ जे क े वल एकटा समतलमे सम मत अधाशमे वभा जत भऽ सक ै त अ छ।"},{"i":311600,"h":"Zygosis","b":"[n.] ; संयु मनक समान।"},{"i":311601,"h":"Zygosperm","b":"[n.] ; समान को शकाक, चाहे एक ै वा अलग-अलग पादपक, अंतव तुक मलनसँ बनल बीजाण। जाइगो पम क तपय शैवाल आ कवक वगमे पाओल जाइत छैक।"},{"i":311602,"h":"Zygosphene","b":"[n.] ; साँपक आ कछु छपकलीक कशे काक तं का चापक अ गला भागपर एकटा म यवत वधन, जे आगाँक चापक पा छला भागमे जाइगै म नामक एकटा ग ामे फट होइत अ छ।"},{"i":311603,"h":"Zygospore","b":"[n.] ; कई जू पोरक संयोगसँ बनल बीजाण — जाइगोजू पोर सेहो कहल जाइत अ छ।"},{"i":311604,"h":"Zygospore","b":"[n.] ; जाइगो पमक समान।"},{"i":311605,"h":"Zygote","b":"[n.] ; यु मनज"},{"i":311606,"h":"zygote","b":"[noun] ; यु मज (जीव)"},{"i":311607,"h":"Zylonite","b":"[n.] ; सेलुलॉयड।"},{"i":311608,"h":"Zymase","b":"[n.] ; एकटा घुलनशील क व वा ए जाइम। ए जाइम देखू।"},{"i":311609,"h":"Zyme","b":"[n.] ; एकटा क व।"},{"i":311610,"h":"Zyme","b":"[n.] ; खमीर / क व / जामन"},{"i":311611,"h":"Zyme","b":"[n.] ; जाइमो टक रोगक रोगजनक त व।"},{"i":311612,"h":"Zymic","b":"[a.] ; क वनसँ संबं धत वा ओकरासँ उ प न — प हने मवश लै टक ए सडक लेल यु त।"},{"i":311613,"h":"Zymogen","b":"[n.] ; एकटा ए जाइम वा रासाय नक क वक पूवगामी मातृ-पदाथ — एहन पदाथपर लागू जे वयं क व न ह होइत ँ आंत रक प रवतन ारा क व उ प न कऽ सक ै त अ छ।"},{"i":311614,"h":"Zymogene","b":"[n.] ; गोलाकार जीवाणक एकटा शार रक समूह जे व वध क ृ तक क वन उ प न करैत अ छ — रोगजनकसँ भ न।"},{"i":311615,"h":"Zymogenic","b":"[a.] ; एकटा न त जाइमोजेन वा क व उ प न करैमे स म।"},{"i":311616,"h":"Zymogenic","b":"[a.] ; जाइमोजेनसँ संबं धत वा ओकरासँ न मत।"},{"i":311617,"h":"Zymologic","b":"[a.] ; जाइमोलॉ जकलक अ य प"},{"i":311618,"h":"Zymological","b":"[a.] ; जाइमोलॉजीसँ संबं धत वा ओकर अनु प।"},{"i":311619,"h":"Zymologist","b":"[n.] ; जाइमोलॉजीमे, वा म दराक क वनमे, नपुण त।"},{"i":311620,"h":"Zymology","b":"[n.] ; म दराक क वनपर एकटा ंथ, वा क वनक स ा त।"},{"i":311621,"h":"Zymome","b":"[n.] ; एकटा गादयु त पदाथ, अ कोहलमे अघुलनशील, लेगु मनसँ मलैत-जुलैत — अखन वन प त फाइ न, वन प त ए बु मन, वा लूटेन क े सन कहल जाइत अ छ।"},{"i":311622,"h":"Zymometer","b":"[n.] ; जाइमो समीटरक अ य प"},{"i":311623,"h":"Zymophyte","b":"[n.] ; एकटा जीवाण-स श क व।"},{"i":311624,"h":"Zymose","b":"[n.] ; इ व टन।"},{"i":311625,"h":"Zymosimeter","b":"[n.] ; व भ न वक म णसँ उ प न क वनक मा ा आ क वनमे ओकरा होयबला ताप मक नधारण करयबला यं ।"},{"i":311626,"h":"Zymosis","b":"[n.] ; एकटा क वन- या; अतः एकटा सा य या जा ह ारा सं ामक रोग वक सत होयब मानल जाइत अ छ।"},{"i":311627,"h":"Zymosis","b":"[n.] ; एकटा जाइमो टक रोग।"},{"i":311628,"h":"Zymotic","b":"[a.] ; एकटा न त वगक रोगक संदभमे। नीचाँ जाइमो टक रोग देखू।"},{"i":311629,"h":"Zymotic","b":"[a.] ; क वनसँ संबं धत, ओकरासँ उ प न, वा ओकरासँ कारण।"},{"i":311630,"h":"Zyophyte","b":"[n.] ; एकटा ता वत वग वा महा वभाग (जाइगोफाइट्स, जाइगोफाइटा, वा जाइगो पोर )क कोनो पादप, जा हमे जनन समान को शकाक संयोगसँ होइत अ छ। तुलना क ऊफाइटसँ।"},{"i":311631,"h":"Zythem","b":"[n.] ; जाइथमक समान।"},{"i":311632,"h":"Zythepsary","b":"[n.] ; एकटा शराबखाना।"},{"i":311633,"h":"Zythum","b":"[n.] ; एकटा ाचीन कारक मा ट पेय; मा ट आ ग मसँ बनल म दरा। Synonyms"},{"i":324387,"h":"z-axis","b":"[n] ; ल-अ ; ला"},{"i":324388,"h":"Zip","b":"[v] ; सङ ् कचत करब ; संवृण करब"},{"i":324389,"h":"Zip ﬁle","b":"[n] ; संवृतस का ; सङ ् कचत स का"},{"i":324390,"h":"Zoom","b":"[n] ; सपक ; उपसपण- अपसपण"},{"i":324391,"h":"Zoom In","b":"[n] ; आकार प रवतन ; जूम"},{"i":324392,"h":"Zoom In","b":"[n] ; उपसपण"},{"i":324393,"h":"Zoom In","b":"[n] ; पैघ कर ; जूम इन"},{"i":324394,"h":"Zoom Out","b":"[n] ; अपसपण"},{"i":324395,"h":"Zoom Out","b":"[n] ; छोट कर ; जूम आउट English Explanation Index"},{"i":344081,"h":"zinc, a white metal used in alloys","b":"[सं ा] ; ज ता ; उ जर रंगक धातु जे म धातु बनयबामे काम अबैत अ छ। Zinc-like metal name; Mithila listed"}]