[{"i":31549,"h":"खाच","b":"[n] ; अथ: जलखच , फल तोड़ स त करबाक जाली। net bag attached to a pole for plucking fruits. ; English: net bag attached to a pole for plucking fruits ; यौ गक: ~ मारब vt डाल मारब। play trick in weighing. ; ु प : [क ु का]"},{"i":31550,"h":"खाच","b":"[n] ; अथ: जौर आ द बटबा/बुनबामे बीच-बीचमे जोड़इबाक साम ी। material added in twisting/knitting. ; English: material added in twisting/knitting"},{"i":31551,"h":"खाचड","b":"[°chair n] ; अथ: नार-पोआरक बनाओल झोड़ा। straw bag. ; English: straw bag"},{"i":31552,"h":"खाचब","b":"अथ: See काँचब। ; देखू: See काँचब"},{"i":31553,"h":"खाचारब","b":"[vt] ; अथ: भा क-भा क त करब। poke and scratch. ; English: poke and scratch"},{"i":31554,"h":"खाचाह","b":"[adj] ; अथ: खाचबाला। scratchy. ; English: scratchy"},{"i":31555,"h":"खाछ","b":"[n] ; अथ: आँचर मो ड़ बनाओल झोड़ा। bag devised by folding the fringe of sari. ; English: bag devised by folding the fringe of sari ; यौ गक: ~ भरब vi स तान होएब। be blessed with a child. Cf खाच ड़, खाची. ; ु प : [क ु त]"},{"i":31556,"h":"खाटब","b":"[vt] ; अथ: नहसँ कनेक-कनेक काटब, जेना सागक मूड़ , अदौड़ । pick with the nails, pluck, rip, nibble. ; English: pick with the nails, pluck, rip, nibble ; यौ गक: खाटी करब vt (बनसीमे माछक) कनेक-कनेक खा ट-खा ट खोर खाएब। (in ﬁshing, said of ﬁsh) nibble bait slowly. ; ु प : [क ु त-]"},{"i":31557,"h":"खाठ","b":"अथ: See खैठ । ; देखू: See खैठ"},{"i":31558,"h":"खाड","b":"[n.] ; English: A local agricultural implement term related to plough. ; देखू: देखू -खाँड तथा बाँच ; े : क ृ ष/लोक-श दावली"},{"i":31559,"h":"खात","b":"[n.] ; अथ: मधुमाछ क छ ा वा बसेरा। ; English: beehive/nest"},{"i":31560,"h":"खात","b":"[n.] ; अथ: /असँवार क े शक घासला-जकाँ प; म थलाक स दभगत श द। ; English: Nest-like disheveled hair; contextual."},{"i":31561,"h":"खासब","b":"[vt] ; अथ: कछु भाग भीतर पैसाए संल न करब। tuck in. ; English: tuck in"},{"i":31562,"h":"खासर","b":"[n] ; अथ: असु वधाकारक आ त त। a burdensome dependent person. ; English: a burdensome dependent person"},{"i":31563,"h":"खा त","b":"[n.] ; अथ: १) एक कार का फल! (२)--प या का घेसला ; English: A type of fruit. ; े : ृ ष/लोक-श दावली"},{"i":31564,"h":"खाइच","b":"[n.] ; अथ: माछक देह परक छलका। ; English: ﬁsh scale"},{"i":31565,"h":"खाइच","b":"[n.] ; अथ: माछक शर र परक छलका। ; English: Scale of a ﬁsh."},{"i":31566,"h":"खाइछ","b":"[n.] ; English: A local agricultural implement term related to plough. ; देखू: देखू आन ; े : क ृ ष/लोक-श दावली"},{"i":31567,"h":"खाइछ","b":"[n.] ; अथ: ना भक अ भागमे साड़ साँ च बनाओल धोकड़ । ; English: front sari pouch/ fold"},{"i":31568,"h":"खाक","b":"[n.] ; English: coughing ; समानाथ : उकासी; खाँसी"},{"i":31569,"h":"खाख","b":"[n.] ; English: 7. cough"},{"i":31570,"h":"खाख","b":"[n.] ; English: cough"},{"i":31571,"h":"खाखब","b":"[vi.] ; English: to cough"},{"i":31572,"h":"खाखल","b":"[adj.] ; English: hollow"},{"i":31573,"h":"खाखल","b":"[n.] ; English: hollow ; समानाथ : फोकला"},{"i":31574,"h":"खाखा करब","b":"[vt.] ; English: to cough"},{"i":31575,"h":"खाखा करब","b":"English: GAY veto | cough"},{"i":31576,"h":"खाघ","b":"[n.] ; अथ: अ भागक ती ण अंश। ; English: Sharp projecting front part of wood."},{"i":31577,"h":"खाच","b":"[n.] ; English: 7. scratch"},{"i":31578,"h":"खाच","b":"[n.] ; English: scratch"},{"i":31579,"h":"खाच","b":"[n.] ; अथ: खाँचीक अ य प। ; English: Lidded fruit basket; variant."},{"i":31580,"h":"खाच","b":"[n.] ; अथ: खाँचीक पा तर। ; English: carrying basket variant"},{"i":31581,"h":"खाच","b":"[n.] ; अथ: खु ीक प। ; English: Twig stub on bamboo; variant."},{"i":31582,"h":"खाच","b":"[n.] ; अथ: ढ कनयु त बाँसक टोकर स ब धी श द। ; English: food-equipment / food- vocabulary term ; े : भोजन/पाक"},{"i":31583,"h":"खाच","b":"[n.] ; अथ: पयाय: झोल अ हार । मूल अथ: सूयादय होने क े पहले क ु छ क ु छ अंधेरा रहना। झोला (सं०) (१) ओ सूखी गरम हवा, जससे फसल लस जाती अ छ। झोलाइल, झाकरल = गरम हवा क े करण लसी फसल (२) पेड़ से फल तोड़ने क े लेल लंबी ल गी क े छोर म बंधा आ छोट जाल। पयाय-खाची, मोरा, जलखार । (३) गाड़ वाना ारा व त बैल ; English: A local agricultural implement term related to fruit, tree, bullock, plough, crop. ; े : क ृ ष/लोक- श दावली"},{"i":31584,"h":"खाच","b":"[n.] ; अथ: पयाय: रोडसीस। मूल अथ: सड़क बनाने एवं मर मत आ द करने क े लेल लया जानेवाला सरकार कर। यह मालगुजार क े साथ ले लया जाता अ छ। (२) रोड सस। | रोड़ा=(सं०) ऊख क े को क े पेट म रस चुने म सहायता प ँचाने क े लेल लगाया गया लकड़ का छोट टुकड़ा। पयाय—रोरा, चं दया; खाच। (२) रोड़ा, क ं कड़, ई ट- प थर का ; े : क ृ ष/लोक-श दावली"},{"i":31585,"h":"खाचड","b":"[n.] ; अथ: तृण वा व सँ बनल भोजन-सहायक साधन स ब धी श द। ; English: food-equipment / food-vocabulary term ; े : व / सलाइ"},{"i":31586,"h":"खाचड","b":"[n.] ; अथ: माछ एक थानसँ दोसर ठाम लऽ जयबाक मोटर । ; English: bundle for carrying ﬁsh"},{"i":31587,"h":"खाचड","b":"[n.] ; अथ: माछ लऽ जयबाक हेतु बा हल साधन। ; English: bundle/net-like ﬁsh carrier ; े : क ृ ष/लोक-श दावली"},{"i":31588,"h":"खाचड","b":"[n.] ; अथ: माछक े एक थानसँ दोसर थान लऽ जयबाक हेतु बाँहल मोटर । ; English: Bundle used to carry ﬁsh from one place to another. ; े : क ृ ष/लोक-श दावली"},{"i":31589,"h":"खाचल","b":"[n.] ; देखू: देखू -- लो'चर ; े : क ृ ष/लोक- श दावली"},{"i":31590,"h":"खाचारब","b":"[vi.] ; English: to poke iz"},{"i":31591,"h":"खाचाह","b":"[adj.] ; English: scratchy"},{"i":31592,"h":"खाचाह","b":"[Adjective/Noun] ; अथ: खरखर वा दोषयु त कपड़ाक बनावट; पर मटक साड़ संगमे। ; English: Coarse or defective cloth texture. ; े : व / सलाइ"},{"i":31593,"h":"खाची मारब","b":"[n.] ; अथ: तौल-माप वहार स ब धी श द। ; English: food-equipment / food- vocabulary term ; े : भोजन/पाक"},{"i":31594,"h":"खाछ","b":"[n.] ; English: bag devised by folding the fringe of sari"},{"i":31595,"h":"खाछ","b":"[n.] ; English: bag devised by: il, folding the fringe of sari ="},{"i":31596,"h":"खा छ भरब","b":"[vt.] ; English: to be blessed with a child"},{"i":31597,"h":"खा छक","b":"[n.] ; अथ: आँचरक खोइंछा/खाछा प; व तु राखबाक दोहरल साड़ -भाग। ; English: Folded sari-end used as a pouch."},{"i":31598,"h":"खाझ","b":"[n.] ; English: bush in a jungle"},{"i":31599,"h":"खाटब","b":"[n./phrase] ; अथ: दा ल, बेसन वा द लहन- ंजन स ब धी श द। ; English: pulse or gram- ﬂour dish term ; े : भोजन/पाक"},{"i":31600,"h":"खाटब","b":"[vt.] ; English: to pluck with nails"},{"i":31601,"h":"खाटल","b":"[v.] ; अथ: (१) सी पोषे क फ ू नगी को ऊपर से तोड़ लेता। (२) -खाटी ई व तु ; े : क ृ ष/लोक- श दावली"},{"i":31602,"h":"खात","b":"[n.] ; English: a nest, a birds) dwelling place, bechive"},{"i":31603,"h":"खाद","b":"[n.] ; अथ: पयाय: खेढ़। मूल अथ: (१) ह रस क े ः ऊपर पाछो बाधने 2 क जगह पर, उसक े | HN नचले भाग का कटा Ue आ अंश। पया०- र खढ् ◌ी, खेढ़ 2 (आ्◌ाहा०). खेहा खाता,खाढ़ , खड् हा, खा (द०-पृ० नहा०), कढ, खेड़ा, खाढ़ । (२) सवेत वण क े शूक (संग) से यु त एक कार का घान। पयो ०- खेदी, खेड़हा। खेढ़ = (संश) ( ; English: A local agricultural variety or object. ; े : क ृ ष/लोक-श दावली"},{"i":31604,"h":"खाप","b":"[n.] ; अथ: (१) भूसा रखने क े डए् आ द का बनाय। आ घर, गं० ड०, मेज २)। (२) बखार क े ऊपर का गोल।कर छ पर। पया ऽ खोप क े मथनी-वषा आई से बचाव े लेल खोप क े ऊपर छाया आ छ पर। (३) स या क े कशा का एक ; े : क ृ ष/लोक-श दावली"},{"i":31605,"h":"खाप","b":"[n.] ; अथ: पयाय: भापड़ा। मूल अथ: खर, पुआल आ द से छाया आ छोट मकान। पयाय-कापड़ , खोपड़ा, खोपड़ , खाप, पलानी, ढाको (सं० प०) ; े : क ृ ष/लोक- श दावली"},{"i":31606,"h":"खाप","b":"[n.] ; अथ: पाछाँ गोल बा हल क े शगु । ; English: Hair bun at the back. ; े : क ृ ष/ लोक-श दावली"},{"i":31607,"h":"खाप","b":"[n] ; अथ: भुसकौड़। chaﬀ box. ; English: chaﬀ box"},{"i":31608,"h":"खापड","b":"[n.] ; अथ: पयाय: सठबा। मूल अथ: एक हार का साग।देशी] | अड़ई-_(सं०) (१) खेत या ख लहान म खड़ क गई झोपड । पयाय-खापड़ , झोपड़ , म का, ◌ापड़ा, क ृ ढा, खापड़ा (द० पू०)। (२) घास- फ ु स क बनी भोपड़ ; े : क ृ ष/लोक-श दावली"},{"i":31609,"h":"खापा-खोपब","b":"[Noun phrase] ; अथ: क े श समेटल आक ृ तक लघु-गु तम प। ; English: Example of short-longest pair for hair bun/knot."},{"i":31610,"h":"खापा-खो पय","b":"[Noun phrase] ; अथ: क े श- व यास स ब धी लघु-गु प। ; English: Example of short-long pair for hair bun term."},{"i":31611,"h":"खापाक नार","b":"[Noun phrase] ; अथ: खापा बाँधबाक सूतक डोर । ; English: Thread cord for tying a bun."},{"i":31612,"h":"खापैल","b":"[n.] ; अथ: छोट खोधी। ; English: Small khodhi ﬁsh basket."},{"i":31613,"h":"खापैल","b":"[n.] ; अथ: छोट खोधी। ; English: small khodhī vessel"},{"i":31614,"h":"खासब","b":"[v.] ; अथ: धोतीक भाग डाँड़मे दबा कऽ समेटब। ; English: to tuck cloth at the waist ; े : व / सलाइ"},{"i":31615,"h":"खासब","b":"[vi.] ; English: to tuck in"},{"i":31616,"h":"खोअओनाइ","b":"[n] ; अथ: भोजन कराएब। feeding. ; English: feeding"},{"i":31617,"h":"खोआ","b":"[n./phrase] ; अथ: ध, खीर वा ध- म ा न या स ब धी श द। ; English: milk, kheer, or dairy-sweet process term"},{"i":31618,"h":"खोआ","b":"[n.] ; English: dchydraded milk"},{"i":31619,"h":"खोआ","b":"[n.] ; English: dehydraded milk"},{"i":31620,"h":"खोआ","b":"[n.] ; अथ: आधु नक मै थली सा ह यक भोजन- व यास-स दभक श द। ; English: modern Maithili literary food-arrangement term ; े : भोजन/पाक"},{"i":31621,"h":"खोआ","b":"[n.] ; अथ: ध खूब आटला पर बचल गील सार पदाथ। ; English: condensed milk solids"},{"i":31622,"h":"खोआ","b":"[n.] ; अथ: ध खूब आटलापर बचल गील सार पदाथ। ; English: reduced milk solids"},{"i":31623,"h":"खोआ","b":"[n.] ; अथ: पयाय: पर। मूल अथ: (१) ख लहान म दाँवने क े लेल छ टी ई तैयार फसल। पयाय-- पौर, पौर , खोह; बड़होरा, ड़होरा (द० मुँ०), ख़आ, खोआ, पोर। (२) दौनी करने क े बाद ओसाने क े लेल अ न और भुसा- मले अ न क रा श ; े : क ृ ष/लोक-श दावली"},{"i":31624,"h":"खोआ","b":"[n.] ; अथ: पयाय: पौर। मूल अथ: (१) फसल क े डंठल से अ न नकलने क े लेल क जानेवाली पहली दौनी। पयाय-खोआ, खुआ ; English: A local agricultural implement term related to plough, crop. ; े : क ृ ष/लोक-श दावली"},{"i":31625,"h":"खोआ","b":"[n.] ; अथ: बीड लगक गाछक मोलायम वा द भाग। ; English: soft edible palm heart ; े : ाणी/वन प त"},{"i":31626,"h":"खोआ","b":"[n.] ; अथ: मै थलीक भोजन-श दावलीक व न- वचार स ब धी श द। ; English: phonological term or example in Maithili food vocabulary ; े : भोजन/पाक"},{"i":31627,"h":"खोआ","b":"[n.] ; देखू: देखू -पेर ; े : क ृ ष/लोक-श दावली"},{"i":31628,"h":"खोआ","b":"[n] ; अथ: 1. गाढ़ कए आटल ध। dehydrated milk of semiliquid form. 2. सुरखीक वा समटीक पातर घोर। groat of course brick-dust or cement. ~ चानी n चानीक एक तर य भेद। a standard of silver. ; English: dehydrated milk of semiliquid form; groat of course brick-dust or cement; a standard of silver"},{"i":31629,"h":"खोआ-म ल","b":"[n./phrase] ; अथ: आधु नक मै थली सा ह यक भोजन- व यास-स दभक श द। ; English: modern Maithili literary food- arrangement term ; े : भोजन/पाक"},{"i":31630,"h":"खोआएब","b":"[cau of खाएब] ; अथ: भोजन कराएब। feed. ; English: feed"},{"i":31631,"h":"खोआड","b":"अथ: See खाँभाड़। ; देखू: See खाँभाड़"},{"i":31632,"h":"खोआय","b":"[n.] ; अथ: मै थल रामायण/महाका क भोजन- व यास-स दभक श द। ; English: Maithil epic/Ramayan food-arrangement term ; े : भोजन/पाक"},{"i":31633,"h":"खोइँछ","b":"[n.] ; English: 7. lap bag made with sari"},{"i":31634,"h":"खोइँछ","b":"[n.] ; English: lap bag made with sari"},{"i":31635,"h":"खोइँछ","b":"[n.] ; अथ: आँचरक कोरमे बाँधल वा धयल व तु/ रा श। ; English: Bundle/pouch made in sari-end."},{"i":31636,"h":"खोइँछ","b":"[n.] ; अथ: खाइछक पा तर; व तु राखय यो य साड़ -फो ड। ; English: sari pouch variant"},{"i":31637,"h":"खोइंच","b":"[n.] ; अथ: खो ाक पा तर। ; English: sweets tray variant"},{"i":31638,"h":"खोइंछ","b":"[n.] ; अथ: आँचरक अ भाग दोह र कऽ व तु राखबाक भाग। ; English: Folded pouch made in sari pallu for holding items."},{"i":31639,"h":"खोइआ","b":"[n.] ; English: 7. shell"},{"i":31640,"h":"खोइआ","b":"[n.] ; English: shell"},{"i":31641,"h":"खोइआ","b":"[n.] ; अथ: मै थलीक भोजन-श दावलीक व न- वचार स ब धी श द। ; English: phonological term or example in Maithili food vocabulary ; े : भोजन/पाक"},{"i":31642,"h":"खोइआ-स","b":"[सं.] ; अथ: कोमल गुटाक कठोर आधार; कड़ा आवरण (जैसे ना रयल, आमक खोइआ) ; े : वन प त ; र ज टर: मै."},{"i":31643,"h":"खोइच","b":"[n.] ; अथ: अ आ वा अ य फल-क दक पातर बा आवरण। ; English: thin outer skin/peel ; े : ाणी/वन प त"},{"i":31644,"h":"खोइच","b":"[n.] ; अथ: माछक शर रपरक छलका। ; English: ﬁsh scale"},{"i":31645,"h":"खोइछ","b":"[n./phrase] ; अथ: सं कार, भार-दोर वा सामा जक भोजन-स दभक श द। ; English: ritual exchange or social food term ; े : भोजन/ पाक"},{"i":31646,"h":"खोइछ","b":"[n.] ; अथ: तृण वा व सँ बनल भोजन-सहायक साधन स ब धी श द। ; English: food-equipment / food-vocabulary term ; े : व / सलाइ"},{"i":31647,"h":"खोइछ-स","b":"[सं.] ; अथ: सघवा ीक गुभ सूचक व ध ; े : सामा जक/परंपरा ; र ज टर: मै."},{"i":31648,"h":"खोइड़आ","b":"[n] ; अथ: 1. ना रक े र आ दक कठोर आवरण। shell. Cf कोइआ। 2. क ु सआरक स ी। bagasse. ; English: shell; bagasse ; ु प : [को षका]"},{"i":31649,"h":"खोइड़च","b":"[n] ; अथ: फलक वचा; माछ आ दक श क। skin of fruit; peelings of pods, nutshell, etc. ; English: skin of fruit; peelings of pods, nutshell, etc."},{"i":31650,"h":"खोइय","b":"[n.] ; अथ: अ आ वा अ य फल-क दक पातर बा आवरण। ; English: thin outer skin/peel ; े : ाणी/वन प त"},{"i":31651,"h":"खोइय","b":"[n.] ; अथ: को ढ़ला गु लीक उपरका मैलछौन भाग। ; English: outer dirty layer of kodhila"},{"i":31652,"h":"खोइय","b":"[n.] ; अथ: खाइचाक पा तर; माछक छलका। ; English: variant of ﬁsh scale"},{"i":31653,"h":"खोइय","b":"[n.] ; अथ: खाइचाक प। ; English: Fish scale; variant."},{"i":31654,"h":"खोइय","b":"[n.] ; अथ: पयाय: बगास। मूल अथ: ईख क स ी, रसर हत ईख का छलका। पयाय-चेफ ु आ, खोइया ; े : क ृ ष/लोक-श दावली"},{"i":31655,"h":"खोइय","b":"[n.] ; अथ: माछक शर रपरक छलका। ; English: ﬁsh scale"},{"i":31656,"h":"खोइय","b":"[n.] ; अथ: मै थलीक भोजन-श दावलीक व न- वचार स ब धी श द। ; English: phonological term or example in Maithili food vocabulary ; े : भोजन/पाक"},{"i":31657,"h":"खोइय","b":"[n.] ; देखू: देखू: कोसा। मूल व म संद भत प ; े : क ृ ष/लोक-श दावली"},{"i":31658,"h":"खोइय","b":"[n.] ; देखू: देखू: खलचोइया। मूल व म संद भत प ; े : क ृ ष/लोक-श दावली"},{"i":31659,"h":"खोइय","b":"[n.] ; देखू: देखू: खा पड़् ◌ी। मूल व म संद भत प ; े : क ृ ष/लोक-श दावली"},{"i":31660,"h":"खोइय","b":"[n.] ; देखू: देखू: खोलड़ । मूल व म संद भत प ; े : क ृ ष/लोक-श दावली"},{"i":31661,"h":"खोइय","b":"[n.] ; देखू: देखू: खो हया। मूल व म संद भत प ; े : क ृ ष/लोक-श दावली"},{"i":31662,"h":"खोइय","b":"[n.] ; देखू: देखू: चेषुआ। मूल व म संद भत प ; े : क ृ ष/लोक-श दावली"},{"i":31663,"h":"खोइय","b":"[n.] ; देखू: देखू: चोषा। मूल व म संद भत प ; े : क ृ ष/लोक-श दावली"},{"i":31664,"h":"खोइय","b":"[n.] ; देखू: देखू: पतौरा। मूल व म संद भत प ; े : क ृ ष/लोक-श दावली"},{"i":31665,"h":"खोइय","b":"[n.] ; देखू: देखू: पोचो। मूल व म संद भत प ; े : क ृ ष/लोक-श दावली"},{"i":31666,"h":"खोइय","b":"[n.] ; देखू: देखू: बक ु ला। मूल व म संद भत प ; े : क ृ ष/लोक-श दावली"},{"i":31667,"h":"खोइय","b":"[n.] ; देखू: देखू: बलको। मूल व म संद भत प ; े : क ृ ष/लोक-श दावली"},{"i":31668,"h":"खोइय","b":"[n.] ; देखू: देखू: बोकला। मूल व म संद भत प ; े : क ृ ष/लोक-श दावली"},{"i":31669,"h":"खोइय","b":"[n.] ; देखू: देखू: स ी। मूल व म संद भत प ; े : क ृ ष/लोक-श दावली"},{"i":31670,"h":"खोइठ","b":"अथ: See खैठ । ; देखू: See खैठ"},{"i":31671,"h":"खोईछ","b":"अथ: 1. See खा छ। 2. जाँतक मुह। mouth of grinding stone. ; देखू: Also खोइछा, खोइ छ"},{"i":31672,"h":"खोईय","b":"[n.] ; देखू: देखू: ॉइचा। मूल व म संद भत प ; े : क ृ ष/लोक-श दावली"},{"i":31673,"h":"खोक","b":"[n.] ; English: 7. cough"},{"i":31674,"h":"खोक","b":"[n.] ; English: cough ; समानाथ : कफ"},{"i":31675,"h":"खोक","b":"[n.] ; English: coughing"},{"i":31676,"h":"खोकस","b":"[n.] ; अथ: अकाठ वा क ु काठ ेणीक लकड़ क नाम। ; English: A poor-timber wood type; reading uncertain."},{"i":31677,"h":"खोकस","b":"अथ: See खोखस (2)। ; देखू: See खोखस (2)"},{"i":31678,"h":"खोक करब","b":"[vt.] ; English: to cough"},{"i":31679,"h":"खोक ला दा दइने घरेलु पेय छमछम","b":"[adv.] ; English: every vito"},{"i":31680,"h":"खोखड","b":"[n.] ; देखू: देखू खाँखड़ ; े : क ृ ष/लोक- श दावली"},{"i":31681,"h":"खोखड़ब","b":"[vt.] ; English: to scrape"},{"i":31682,"h":"खोखड़ब","b":"[vt] ; अथ: खखोड़ब, घषणसँ उखाड़ब। scrape, rake up. ; English: scrape, rake up ; यौ गक: खोखड़न n खखो ड़क हटाओल अंश। scrapings. खोखड़ना,°नी n खोखड़बाक उपकरण। scraper."},{"i":31683,"h":"खोखन","b":"[adj] ; अथ: मोट-डाँट ( न दामे)। stout, corpulent (der). ; English: stout, corpulent (derogatory)"},{"i":31684,"h":"खोखबल","b":"[n.] ; अथ: चतकावर पाँ खवला म यम आक ृ तक मधुमाछ । ; English: medium bee variety"},{"i":31685,"h":"खोखर","b":"[n.] ; देखू: देखू: धोधर। मूल व म संद भत प ; े : क ृ ष/लोक-श दावली"},{"i":31686,"h":"खोखरन","b":"[n.] ; अथ: खखोरना उपकरणक प। ; English: Spiked harrow; variant."},{"i":31687,"h":"खोखरन","b":"[n.] ; अथ: खखोरनाक अ य प। ; English: Toothed grain-stirring implement; variant. ; े : भोजन/पाक"},{"i":31688,"h":"खोखरन","b":"[n.] ; अथ: खोखरनाक प। ; English: Spiked soil-crust breaker; variant. ; े : ृ ष/लोक-श दावली"},{"i":31689,"h":"खोखरन","b":"[n.] ; अथ: खोखरनाक प। ; English: Toothed grain-stirring implement; variant. ; े : भोजन/पाक"},{"i":31690,"h":"खोखरन","b":"[n.] ; अथ: धान लारबाक दाँतदार उपकरणक प। ; English: Rake-like grain-stirring tool; variant. ; े : भोजन/पाक"},{"i":31691,"h":"खोखला- वश","b":"[ व.] ; अथ: भीतर सँ फाक ; े : अव था ; र ज टर: ह. त सम"},{"i":31692,"h":"खोखवला म ख","b":"[n.] ; अथ: चतकाबर पाँ खवला म यम मधुमाछ । ; English: medium spotted-wing bee"},{"i":31693,"h":"खोखस","b":"[n.] ; अथ: अ य त छोट ेताभ माछक भेद। ; English: very small whitish ﬁsh type"},{"i":31694,"h":"खोखस","b":"[n.] ; अथ: अ य त छोट ेताभ/सइर वहीन माछ। ; English: Very small whitish or scaleless ﬁsh."},{"i":31695,"h":"खोखस","b":"[n.] ; अथ: खोखसक पा तर। ; English: variant of ﬁsh internal lung-like part"},{"i":31696,"h":"खोखस","b":"[n.] ; अथ: खोखसक प। ; English: Air- bladder/lung-like inner part; variant."},{"i":31697,"h":"खोखस","b":"[n.] ; अथ: खोखसाक पा तर। ; English: variant of khokhsa tiny ﬁsh"},{"i":31698,"h":"खोखस","b":"[n.] ; अथ: खोखसाक प। ; English: Variant of खोखसा ﬁsh."},{"i":31699,"h":"खोखस","b":"[n.] ; अथ: नाम आक ृ तक मुँहवला माछ। ; English: hollow-mouthed ﬁsh"},{"i":31700,"h":"खोखस","b":"[n.] ; अथ: माछक फ े फड़ा-जकाँ भीतर भाग। ; English: Air-bladder/lung-like inner part of a ﬁsh."},{"i":31701,"h":"खोखस","b":"[n.] ; अथ: माछक फ े फड़ा/भीतरक खोखल भाग। ; English: ﬁsh lung-like hollow part"},{"i":31702,"h":"खोखस","b":"[n.] ; अथ: माछक फ े फड़ावला भीतरका भाग। ; English: lung-like internal part of a ﬁsh"},{"i":31703,"h":"खोखस","b":"[n] ; अथ: 1. एक गाछ जकर पातक दोना बनैत अ छ, काकोटु ब रका। a tree known for long ﬁbrous leaves ﬁt for making cup-like pots. 2. पेटक वचापर पड़ल रेखा। creases formed on belly. ; English: a tree with long ﬁbrous leaves; creases formed on belly"},{"i":31704,"h":"खोखसाह","b":"[adj] ; अथ: उपरसँ मोटाएल क तु भतरसँ बल, फ ु लफ ु लाह (देह)। (body) looking strong and stout, but really weak. ; English: (body) looking strong and stout but really weak"},{"i":31705,"h":"खोङच","b":"[n.] ; अथ: खाँचीक पा तर। ; English: carrying basket variant"},{"i":31706,"h":"खोङच","b":"[n.] ; अथ: ढ कनयु त बाँसक टोकर स ब धी श द। ; English: food-equipment / food- vocabulary term ; े : भोजन/पाक खोङ"},{"i":31711,"h":"खोच","b":"[n.] ; अथ: कपड़ाक टुकड़ लागल फाटल भाग। ; English: patched torn portion ; े : व / सलाइ"},{"i":31712,"h":"खोच","b":"[n.] ; अथ: कपड़ाक टुकड़ लागल फाटल भाग। ; English: Torn part patched with a cloth piece. ; े : व / सलाइ"},{"i":31713,"h":"खोच","b":"[n.] ; अथ: कपड़ामे फ ँ सल व तु वा तनाव सँ बनल फटबाक आक ृ त। ; English: snag/tear mark ; े : व / सलाइ"},{"i":31714,"h":"खोचब","b":"[v.] ; अथ: शर रमे खो च गोदनाक आक ृ त उभारब। ; English: To prick/incise for tattooing."},{"i":31715,"h":"खोचर","b":"[n.] ; अथ: काइम खतम भेल थानपर देल नव काइम। ; English: inserted replacement strip"},{"i":31716,"h":"खोचर","b":"[n.] ; अथ: खोचरक पा तर। ; English: replacement strip variant"},{"i":31717,"h":"खोचर","b":"[n.] ; अथ: खोचरक प। ; English: Replacement weaving strip; variant."},{"i":31718,"h":"खोचर","b":"[n.] ; अथ: बनैत- बनैत काइम समा त भेला पर ओ ह थान पर देल नव काइम। ; English: Inserted replacement strip during weaving."},{"i":31719,"h":"खोचर","b":"[n.] ; देखू: देखू लो'चर ; े : क ृ ष/लोक- श दावली"},{"i":31720,"h":"खोचाह","b":"[adj.] ; अथ: खाचयु त बाँस। ; English: Bamboo with twig stubs."},{"i":31721,"h":"खोज","b":"[adj.] ; English: enquiring, investigation"},{"i":31722,"h":"खोज","b":"[adj.] ; English: search enquiring, investigation, (Gre khot n.. fault, defect, vice, f a"},{"i":31723,"h":"खोज","b":"[n.] ; English: 7. scarch, ques to investigation, exploration, research, enquiry"},{"i":31724,"h":"खोज","b":"[n.] ; English: search, quest investigation, exploration, research, engi"},{"i":31725,"h":"खोज","b":"[n] ; अथ: खोजू ; English: search"},{"i":31726,"h":"खोज करब","b":"[vt.] ; English: ve investigate, look into/for, inquire into, search"},{"i":31727,"h":"खोज करब","b":"English: karab 7A ve re, investigate, look into/for, inquire into, seek search"},{"i":31728,"h":"खोज सहेज","b":"[n] ; अथ: खोज सहेजू ; English: save search"},{"i":31729,"h":"खोज-स","b":"[सं.] ; अथ: अनुस धान, अ वेषण ; े : या ; र ज टर: मै."},{"i":31730,"h":"खोजखबर","b":"[n.] ; English: 7. search investigation a"},{"i":31731,"h":"खोजखबर","b":"[n.] ; English: investigation"},{"i":31732,"h":"खोजड","b":"[n.] ; देखू: देखू भब वयाएल ; े : क ृ ष/लोक- श दावली"},{"i":31733,"h":"खोजड","b":"[v.] ; देखू: देखू _ बजमार ; े : क ृ ष/लोक- श दावली"},{"i":31734,"h":"खोजतलास","b":"[n.] ; English: investigation 7. 7. investigation"},{"i":31735,"h":"खोजतलास","b":"English: investigation"},{"i":31736,"h":"खोजतलास सडक","b":"[n.] ; English: mvestigation ; समानाथ : गवेषण"},{"i":31737,"h":"खोजनाइ","b":"[n.] ; English: 77. 7. investigation"},{"i":31738,"h":"खोजनेवाल","b":"[n.] ; अथ: पयाय: र नहार। मूल अथ: (१) पानी से भरे मोट को खाली करनेवाला मनु य (गं० उ०)। पयाय- छनवा, मोटढरवा, (२) खोजनेवाला। 1 ; े : क ृ ष/ लोक-श दावली"},{"i":31739,"h":"खोजब","b":"[vt] ; अथ: अ वेषण करब। search, seek. ; English: search, seek ; यौ गक: खोज n. ~ पुछार n ताक-हेर, अ वेषण। enquiry, looking after. खोजार See पुछार ."},{"i":31740,"h":"खोजब","b":"English: A ve search for"},{"i":31741,"h":"खोजब","b":"English: TA vel search for"},{"i":31742,"h":"खोजबीज","b":"English: khojabij"},{"i":31743,"h":"खोजबीज करब","b":"English: karab"},{"i":31744,"h":"खोजबीन","b":"[n.] ; English: enquiry"},{"i":31745,"h":"खोजबीन करब","b":"[vt.] ; English: to search, look for"},{"i":31746,"h":"खोजबीन तह ककात","b":"[n.] ; English: enquiry"},{"i":31747,"h":"खोजसँ खोज फो डर बनाउ","b":"[n] ; अथ: खोजसँ खोज फो डर बनाबू ; English: create search folder from search"},{"i":31748,"h":"खोझ","b":"[n.] ; English: bush in a jungle"},{"i":31749,"h":"खोझ","b":"अथ: See झोझ। ; देखू: See झोझ"},{"i":31750,"h":"खो","b":"[n.] ; अथ: मठाइ बेचबाक चा कात घेरावाला काठक बासन। ; English: wooden sweets tray/box"},{"i":31751,"h":"खोट","b":"[n.] ; English: fault, defect, Vice, Ma"},{"i":31752,"h":"खोट","b":"[n.] ; English: slt ; समानाथ : घ ी; चूक"},{"i":31753,"h":"खोट","b":"[n] ; अथ: ु ट, दोष, अशु । ﬂaw, defect, impurity. ; English: ﬂaw, defect, impurity ; देखू: adj अधम, अप म त। debased, impure. Also खाट."},{"i":31754,"h":"खोटका-स","b":"[सं.] ; अथ: १. अ न टक भय; २. अशोच ; े : भाव ; र ज टर: मै."},{"i":31755,"h":"खोटब","b":"[v.] ; अथ: भोजन-काय- ापारसँ स ब यापद। ; English: verb related to food preparation or eating process ; े : भोजन/ पाक"},{"i":31756,"h":"खोटर हत","b":"[adj.] ; English: fa"},{"i":31757,"h":"खोटर हत","b":"[adj.] ; English: ﬁa"},{"i":31758,"h":"खोटल","b":"[n.] ; अथ: खटोलीक पाठ प; क धवा सवार । ; English: Shoulder-borne cot carrier; variant."},{"i":31759,"h":"खोटल","b":"[n.] ; अथ: खु टयाक पा तर। ; English: tiny nose stud variant"},{"i":31760,"h":"खोटल","b":"[n.] ; अथ: नाकक छेदमे प हरबाक छकक एक प। ; English: A form of nose chhak worn in the nostril."},{"i":31761,"h":"खो टल","b":"[n.] ; अथ: खु टयाक पा तर। ; English: tiny nose stud variant"},{"i":31762,"h":"खो टल","b":"[n.] ; अथ: खु टलाक पा तर। ; English: central-bead earring variant खो टला कणफ"},{"i":31764,"h":"खोड","b":"[adj] ; अथ: 1. पड़, नागड़। lame. 2. ख डत, अपूण। incomplete, imperfect. ; English: lame; incomplete, imperfect ; यौ गक: n जल यासँ भेल खा ध। ditch caused by gush of water, gully. Also खोड़।"},{"i":31765,"h":"खोड","b":"[adj] ; अथ: मुहनोर। timid in speaking. ; English: timid in speaking"},{"i":31766,"h":"खोड","b":"[n] ; अथ: टूटल बा हक खा ध। breach on the road. ; English: breach on the road"},{"i":31767,"h":"खोडय","b":"[n.] ; अथ: नेबोक उपरका भाग। ; English: top part of lemon"},{"i":31768,"h":"खोडह","b":"[n.] ; अथ: खाघक प। ; English: Sharp projecting wood point; variant."},{"i":31769,"h":"खोडहैल","b":"[n.] ; अथ: खापैला/छोट खोधीक पा तर। ; English: variant of small ﬁsh vessel"},{"i":31770,"h":"खोडहैल","b":"[n.] ; अथ: खापैलाक प। ; English: Small ﬁsh basket; variant."},{"i":31771,"h":"खोड़- वश","b":"[ व.] ; अथ: १. पूण प मे एक अंशक कमी; २. अंगभंग ; े : अव था/शर र ; र ज टर: मै."},{"i":31772,"h":"खोड़च","b":"[n] ; अथ: बाँसक एक पा । a bamboo- basket. ; English: a bamboo-basket"},{"i":31773,"h":"खोड़न","b":"[n] ; अथ: त भाकार बनुआ बासन। cylindrical basket. ; English: cylindrical basket ; यौ गक: खोड़ d."},{"i":31774,"h":"खोड़ब","b":"[vt] ; अथ: खाचा ड़क तर-उपर करब, लाड़ब। stir, poke. ; English: stir, poke ; यौ गक: खोड़ना, खोड़नाठ n खोड़बाक काठ । poker, stirrer. ; ु प : [शोद-]"},{"i":31775,"h":"खोड़ब ह","b":"[n] ; अथ: जलक वाहसँ टुटल बा ह। breached road. ; English: breached road"},{"i":31776,"h":"खोड़र","b":"[n] ; अथ: खोधर। cavity. ; English: cavity ; ु प : [कोटर]"},{"i":31777,"h":"खोड़ल","b":"[n.] ; देखू: देखू: खधघुली। मूल व म संद भत प ; े : क ृ ष/लोक-श दावली"},{"i":31778,"h":"खोड़सञ","b":"[n] ; अथ: या ामे असमथ बूढ़, नेना आ दक सङ ् ग लगनाइ। a companion proving burden some in journey. ; English: a companion proving burden some in journey"},{"i":31779,"h":"खोड़ह","b":"[n] ; अथ: 1. पनेसी आ द खेलक प का। board of chess and the like. 2. हरक खात। notches in plough. 3. पहाड़ा। multiplication table. ; English: board of chess; notches in plough; multiplication table"},{"i":31780,"h":"खोड़ह","b":"अथ: See खोड़हा। ; देखू: See खोड़हा"},{"i":31781,"h":"खो ड़आ","b":"[n] ; अथ: कलई करबामे राड़ गलएबाक पा । clay pot for smelting lead for tinplating, crucible. ; English: clay pot for smelting lead for tinplating, crucible"},{"i":31782,"h":"खोड़ेय","b":"[n.] ; अथ: छोट क ाक एक पा तर। ; English: variant of small chopper"},{"i":31783,"h":"खोड़ैय","b":"[सं ा] ; अथ: छोट क ी/काती जकाँ धारदार औजार। ; English: small blade variant"},{"i":31784,"h":"खोत","b":"[n.] ; English: 7. nest"},{"i":31785,"h":"खोत","b":"[n.] ; English: a nest, a bird's | n dwelling place, bechive"},{"i":31786,"h":"खोत","b":"[n.] ; English: nest;. hodaparni). n. a of tattooing profession $; FTA ve. to carve ddaha. n. tattoo 54. to peck, dig 1; 7. cleft lip honahi. n. narrow between 9. n. vaccination, inoculation 9. n. pigeon house, alcove 152(1; 7. a thatched cottage 151. 7. hut () 7. ball-like yt of hair, bun \\Obhab. fe. vt. to sow seeds in hobhir 77.. a hog house; n. chicken house, age, cell khoranathi); n. vooden log horak. n. dose, diet, intake. ». maintenance nce 51. n. (skin-made) holster, tholab 7%. vi. to open, ¢, Untic, unfasten 61; n. cye-band for BR the eyes of animals AT. ». rivulet, stream i deb).. ve. to lo help others) 12.. () vi. to"},{"i":31787,"h":"खोत","b":"[n] ; अथ: प ीक घर। nest. ; English: nest ; देखू: Also खाता."},{"i":31788,"h":"खोद","b":"[n] ; अथ: ई र (इ लाममे)। God (in Islam). ; English: God (in Islam) ; ु प : [P]"},{"i":31789,"h":"खोद-स","b":"[सं.] ; अथ: कोङब, ज ङ जगाएव ; े : या ; र ज टर: मै."},{"i":31790,"h":"खोदनपार","b":"अथ: See खोषपारनी। ; देखू: See खोषपारनी"},{"i":31791,"h":"खोदल","b":"[n.] ; अथ: (१) कोठ या दीवार क े ; े : क ृ ष/ लोक-श दावली"},{"i":31792,"h":"खोदह","b":"[n.] ; English: tattoo"},{"i":31793,"h":"खोध","b":"[n.] ; अथ: मारल माछ रखबाक छोट गोल बासन। ; English: Small round basket/vessel for keeping caught ﬁsh."},{"i":31794,"h":"खोध","b":"[n.] ; अथ: मारल माछ राखबाक छोट गोल बासन। ; English: small round vessel for keeping caught ﬁsh"},{"i":31795,"h":"खोध","b":"अथ: See under खोधब। ; देखू: See under खोधब"},{"i":31796,"h":"खोधपाडुन","b":"[n.] ; अथ: गोदना गोद नहार नट जा तक ी। ; English: Female tattooer, traditionally of the Nat community."},{"i":31797,"h":"खोधब","b":"[v.] ; अथ: गहनापर आक ृ त खोदबाक या। ; English: To engrave/carve ornament designs."},{"i":31798,"h":"खोधब","b":"[v.] ; अथ: धातु, गहना वा देहपर खो द आक ृ त बनायब। ; English: To engrave/incise."},{"i":31799,"h":"खोधब","b":"[v.] ; अथ: न काशी करबाक या। ; English: to engrave"},{"i":31800,"h":"खोधब","b":"[vt] ; अथ: घरगर/नोकगर उपकरण गड़ाए-गड़ाए खा ध करब। dig, excavate; engrave, carve. ; English: dig, excavate; engrave, carve ; यौ गक: खोध-बेय n गहन पर ण। probe. खोधपारनी n खोधा पारबाक वसायबाली म हला। female who does tattoo as an occupation. खोधर n छोट खा ध। cavity. °धया n वचामे रङ पा न बनाओल च । tattoo. खोधाड़ n उ खनन। excavation, digging. खोधाड़ 'n छोट खा ध। cavity. खोधामा n उ करण। engraving work. खा धआएब vt खो ध-खो ध खपबैत जाएब। consume bit by bit, nibble. ; ु प : [ ोद-]"},{"i":31801,"h":"खोधर","b":"[n.] ; अथ: खोधरक प; सड़ल लकड़ क खा ध। ; English: Rot-hole; variant."},{"i":31802,"h":"खोधर","b":"[n.] ; अथ: सड़ल लकड़ क भाग छुटलापर बनल खा ध। ; English: Rot-hole in wood."},{"i":31803,"h":"खोधर","b":"[°dhair n] ; अथ: 1. गाछ/काठमे कएल खा ध। hollow in a tree. 2. दाँत आ दमे भेल त। notch, jag. ; English: hollow in a tree; notch, jag ; ु प : [कोटर]"},{"i":31804,"h":"खोधल","b":"[n.] ; अथ: कोठ क बीचमे व तु रखबाक घनाकार खाली भाग ; English: inner storage cavity of bin"},{"i":31805,"h":"खोधल","b":"[n.] ; अथ: कोठ क बीचमे व तु राखक घनाकार खाली भाग। ; English: cubical cavity inside a bin"},{"i":31806,"h":"खोधल","b":"[n.] ; अथ: ब सा वा क तोरक भीतरक छोट वभाग। ; English: Small compartment."},{"i":31807,"h":"खोधाम","b":"[n.] ; अथ: आम/आमा/अ मा ययसँ सा धत श दक उदाहरण। ; English: suﬃx आम/आमा example ; े : सा ह य/ ाकरण"},{"i":31808,"h":"खोधाम","b":"[n.] ; अथ: काठ पर खोधल अलंकरण/आक ृ त। ; English: Carved pattern or engraving on wood."},{"i":31809,"h":"खोधाम","b":"[n.] ; अथ: न कासीक पा तर; खोधल आक ृ त। ; English: carved design variant"},{"i":31810,"h":"खोधाम","b":"[n.] ; अथ: म थलाक भोजन-श दावलीक ृ यययु त श द। ; English: Mithila verbal/ krit suﬃx form ; े : भोजन/पाक"},{"i":31811,"h":"खोधाम","b":"[n.] ; अथ: साँचपर खोधल आक ृ त ; English: carved design"},{"i":31812,"h":"खो ध ल","b":"[n.] ; देखू: देखू लोढ़ली-२ ; े : क ृ ष/लोक- श दावली"},{"i":31813,"h":"खोन","b":"[adj] ; अथ: कटल ठोरबाला। hare-lipped. ; English: hare-lipped"},{"i":31814,"h":"खोन","b":"[n.] ; English: cleft lip"},{"i":31815,"h":"खोन","b":"[n.] ; अथ: खो हक पा तर। ; English: whirlpool hollow variant"},{"i":31816,"h":"खोन","b":"[n.] ; अथ: खो हक प। ; English: Deep whirlpool pit; variant."},{"i":31817,"h":"खोनह","b":"[n.] ; English: narrow place inbetween"},{"i":31818,"h":"खोनह","b":"[n] ; अथ: घरक साँक ु ल कोण। dark corner of a room. ; English: dark corner of a room ; ु प : [कोण-]"},{"i":31819,"h":"खोनाठ","b":"[n] ; देखू: See खोरनाठ। खोनाठ d. ; ु प : [शोदनका ]"},{"i":31820,"h":"खो ह","b":"[n.] ; अथ: भँवर पड़ल थानक गहीर खा ध। ; English: Deep pit made by a whirlpool."},{"i":31821,"h":"खो ह","b":"[n.] ; अथ: भंवर पड़ल थानक ग हर खा ध। ; English: deep hollow formed by a whirlpool"},{"i":31822,"h":"खो ह","b":"अथ: See खोता। ; देखू: See खोता"},{"i":31823,"h":"खो ह लआर","b":"[n.] ; अथ: म थलाक डोम जा त/ े ीय- वभाजन स ब धी श द। ; English: Mithila caste/ community term"},{"i":31824,"h":"खोप","b":"[n.] ; English: ball-like top-knot of hair"},{"i":31825,"h":"खोप","b":"[n.] ; English: vaccination ; समानाथ : टीका; पाच"},{"i":31826,"h":"खोप","b":"[n.] ; अथ: खापाक उलटल वा लघु प। ; English: Hair-bun variant; diminutive/ related form. ; े : भोजन/पाक"},{"i":31827,"h":"खोप","b":"[n.] ; अथ: खापाक ऊपर उनटाओल प। ; English: Turned-up hair knot/bun. ; े : भोजन/पाक"},{"i":31828,"h":"खोप","b":"[n.] ; अथ: छोट खोपा अथवा खोपाक पा तर। ; English: Small hair bun or variant of bun. ; े : भोजन/पाक"},{"i":31829,"h":"खोप","b":"[n.] ; अथ: बा हल क े शक गोल गु । ; English: Hair bun. ; े : क ृ ष/लोक-श दावली"},{"i":31830,"h":"खोप","b":"[n.] ; अथ: माथ वा पाछू भागमे ब हल गोल े शरचना। ; English: Hair bun, usually tied at the back or top. ; े : क ृ ष/लोक-श दावली"},{"i":31831,"h":"खोप","b":"[n.] ; अथ: मुग रखबाक पौती-आक ृ तक बीनल बासन। ; English: woven poultry basket/ coop"},{"i":31832,"h":"खोप","b":"[n.] ; अथ: मुग रखबाक लेल सा ट कऽ बीनल पौती-आक ृ तक बासन। ; English: Woven bamboo chicken coop/container."},{"i":31833,"h":"खोप","b":"[n] ; अथ: 1. अधवृ ाकर छाजन। dome-like roof, canopy. 2. परबाक घर। pigeon's house. ; English: dome-like roof, canopy; pigeon's house ; यौ गक: खोपड़ [खपट] n कपाल, ख पर। skull. खोपड़ , खोप ड़ n अधवृ ाकर आवरणबाला अ थायी छोट घर, जेना खेतक रखबार आ दक। hut of low roof."},{"i":31834,"h":"खोप","b":"[n] ; अथ: समे टक गोलाकार बा हल क े स। ball- like top-knot of hair, bun. ; English: ball- like top-knot of hair, bun ; यौ गक: खोपी d."},{"i":31835,"h":"खोप-स","b":"[सं.] ; अथ: परबाक रहैक क ृ लम थान ; े : थान ; र ज टर: मै."},{"i":31836,"h":"खोपड","b":"[n.] ; English: hut"},{"i":31837,"h":"खोपड","b":"[n.] ; अथ: नब ध/लोकसा ह यक भोजन- व यास-स दभक श द। ; English: essay/folk- literature food-arrangement term ; े : भोजन/पाक"},{"i":31838,"h":"खोपड","b":"[n.] ; अथ: पयाय: झोपड़ । मूल अथ: मचान क े ऊपर छाँह क े लेल बना आ गोल छ पर (गं० उ०)। पयाय- खोपड़ , छुपर (उ० प० मै०), छाही, लगौर , छपरा (गं०, द°), म का (गं०, द° प°), छपर (गं०, द० पू०) ; े : ृ ष/लोक-श दावली"},{"i":31839,"h":"खोपड","b":"[n.] ; अथ: पयाय: भापड़ा। मूल अथ: खर, पुआल आ द से छाया आ छोट मकान। पयाय-कापड़ , खोपड़ा, खोपड़ , खाप, पलानी, ढाको (सं० प०) ; े : क ृ ष/लोक- श दावली"},{"i":31840,"h":"खोपड -स","b":"[सं.] ; अथ: १. बाध बोनक खोह जका भू म सं लागल अ थायी घर; २. माथक उपरक भाग ; े : थान/ शर र ; र ज टर: मै."},{"i":31841,"h":"खोपब ह","b":"[n.] ; अथ: खोपा ब हबाक डोर । ; English: Hair-tie for binding a bun."},{"i":31842,"h":"खोपब ह","b":"[n.] ; अथ: खोपा ब हबाक फ ु दना लागल डोर । ; English: cord for tying a hair bun"},{"i":31843,"h":"खोपब ह","b":"[n] ; अथ: खोपा ब हबाक डोर । hair band. ; English: hair band"},{"i":31844,"h":"खोपब ह यौ गक","b":"[Noun phrase] ; अथ: खोपा आ बा हक संयोगसँ बनल क े श बाँधबाक प। ; English: Compound hair-binding form. खोपा ऊ"},{"i":31846,"h":"खोपा खोलब","b":"[Verb phrase] ; अथ: बा हल खोपा खोलबाक या। ; English: To loosen/open a hair bun. ; े : क ृ ष/लोक-श दावली"},{"i":31847,"h":"खोपा बा हब","b":"[Verb phrase] ; अथ: क े शक खोपा बनाकऽ बा हब। ; English: To tie hair into a bun."},{"i":31848,"h":"खोपा-चोटी ब हायब","b":"[Verb phrase] ; अथ: क े शक खोपा आ चोटीमे बनबयबाक या। ; English: To have hair dressed in bun and braid. ; े : व / सलाइ"},{"i":31849,"h":"खोपा-स","b":"[सं.] ; अथ: समे ट कय कला क ष एकठां बा हल क ै व व यास ; े : व तु ; र ज टर: मै."},{"i":31850,"h":"खोपाक जालदार गहन","b":"[Noun phrase] ; अथ: खोपाक चा दस लगाओल जालदार आभूषण। ; English: Net-like ornament worn around the hair bun. ; े : भोजन/पाक खोपामे फ"},{"i":31852,"h":"खोभ","b":"[n.] ; अथ: खाघक प। ; English: Sharp wood projection; variant."},{"i":31853,"h":"खोभ","b":"[n.] ; अथ: चाउरसँ ा त भुजाइ यो य अ न- प। ; English: parched rice product ; े : भोजन/ पाक"},{"i":31854,"h":"खोभ","b":"[n] ; अथ: 1. नोकबाला ड टा। pin, pointed stick. 2. एक तृण जकर बीआ लाभा होइत अ छ। a grass bearing ﬁne edible grains. 3. d of खोभ। ; English: pin, pointed stick; a grass bearing ﬁne edible grains"},{"i":31855,"h":"खोभ","b":"[n] ; अथ: ठे ड़ आ दक वतुल अ भाग। rounded end of staﬀ. ; English: rounded end of staﬀ ; यौ गक: खोभब nvt ड टाक र (वतुल अ )सँ भूर कए-कए बीआ रोपब। sow seeds in the holes."},{"i":31856,"h":"खोभटब","b":"[vt] ; अथ: उपराग देब। complain. ; English: complain ; यौ गक: खोभाटब cau."},{"i":31857,"h":"खोभ ट","b":"[n.] ; अथ: खु भयाक पा तर। ; English: bamboo spike variant"},{"i":31858,"h":"खोभ ट","b":"[n.] ; अथ: खु भयाक प। ; English: Pointed bamboo peg/tool; variant."},{"i":31859,"h":"खोभर","b":"[n.] ; अथ: खोभारक पा तर। ; English: animal enclosure variant ; े : ाणी/ वन प त"},{"i":31860,"h":"खोभर","b":"[n.] ; अथ: खोभारक प। ; English: Large bamboo enclosure/storage pen; variant."},{"i":31861,"h":"खोभाड","b":"[n] ; अथ: सुगरक घर। piggery. ; English: piggery"},{"i":31862,"h":"खोभार","b":"[n.] ; अथ: घरमे व तु/सामान रखबाक पैघ बेढ़। ; English: Large bamboo enclosure/ storage pen."},{"i":31863,"h":"खोभार","b":"[n.] ; अथ: माल-जाल रखबाक पैघ बेढ़। ; English: large bamboo enclosure for animals ; े : ाणी/वन प त"},{"i":31864,"h":"खोभार","b":"[n.] ; देखू: देखू --दवड़ ; े : क ृ ष/लोक- श दावली"},{"i":31865,"h":"खोम","b":"[n] ; अथ: मनमे अमङ ् गलक आशङ ् का। evil apprehension. ; English: evil apprehension ; यौ गक: खोमटार, खोमाह adj अ न क आशङ ् का करैत रहबाक वभावबाला। eerie, of apprehensive nature."},{"i":31866,"h":"खोमच","b":"[n.] ; अथ: खो ाक पा तर। ; English: portable sweets tray variant"},{"i":31867,"h":"खोमचा-स","b":"[सं.] ; अथ: च ल फ र बेचैक लेल व तु रखैक ै ल आ उ थर काठक वासन ; े : उपकरण/ वसाय ; र ज टर: मै."},{"i":31868,"h":"खोर","b":"[n.] ; English: chicken house"},{"i":31869,"h":"खोर","b":"[n.] ; अथ: अपखोरा समूहक पा तर। ; English: drinking bowl variant"},{"i":31870,"h":"खोर","b":"[n.] ; अथ: अपखोराक सं त प; पा न पीबाक बासन। ; English: bowl for drinking water"},{"i":31871,"h":"खोर","b":"[n.] ; अथ: खोरक पा तर। ; English: variant of curd-setting pot"},{"i":31872,"h":"खोर","b":"[n.] ; अथ: खोरक पा तर। ; English: variant of khor vessel"},{"i":31873,"h":"खोर","b":"[n.] ; अथ: खोरक प। ; English: Curd- setting pot; variant."},{"i":31874,"h":"खोर","b":"[n.] ; अथ: दही जमयबाक चाकर मुँह, कम गहीर पेट आ कानवला तौला। ; English: shallow wide- mouthed curd-setting pot"},{"i":31875,"h":"खोर","b":"[n.] ; अथ: दही पौड़बाक कम गँहीर चाकर मुँहवला तौला। ; English: shallow wide-mouthed curd-setting vessel"},{"i":31876,"h":"खोर","b":"[n.] ; अथ: दही पौड़बाक चाकर मुँह, कम गँहीर तौला। ; English: Wide-mouthed shallow curd-setting pot."},{"i":31877,"h":"खोर","b":"[n.] ; अथ: दही पौरबाक चाकर-मुँह कम-गँहीर तौला ; English: shallow earthen curd-setting vessel"},{"i":31878,"h":"खोर","b":"[n.] ; अथ: प नपीयाक स श फ ू ल/काँसक बासन ; English: drinking bowl type"},{"i":31879,"h":"खोर","b":"[n.] ; अथ: यय-योजनासँ मशः बनल श द- ंखला। ; English: derivational chain example ; े : सा ह य/ ाकरण"},{"i":31880,"h":"खोर","b":"[n.] ; देखू: देखू -भट्◌ ् क़ ; े : क ृ ष/लोक- श दावली"},{"i":31881,"h":"खोर","b":"[n.] ; देखू: देखू मटका ; े : क ृ ष/लोक-श दावली"},{"i":31882,"h":"खोर","b":"[n.] ; देखू: देखू रास ; े : क ृ ष/लोक-श दावली"},{"i":31883,"h":"खोर","b":"[n.] ; देखू: देखू: क ु इमूनन। मूल व म संद भत प ; े : क ृ ष/लोक-श दावली"},{"i":31884,"h":"खोर","b":"[n.] ; देखू: देखू: छ ना। मूल व म संद भत प ; े : क ृ ष/लोक-श दावली"},{"i":31885,"h":"खोर","b":"[n.] ; देखू: देखू: नाद। मूल व म संद भत प ; े : क ृ ष/लोक-श दावली"},{"i":31886,"h":"खोर","b":"[n] ; अथ: 1. मुरगा-घर। chicken house. 2. अनाजक ढेर। heap of food grain. 3. ध गृहबाक मटका। earthen churning vessel. ; English: chicken house; heap of food grain; earthen churning vessel"},{"i":31887,"h":"खोर","b":"अथ: See खोर (2-3)। ; देखू: See खोर (2-3)"},{"i":31888,"h":"खोर-मयूर","b":"[n] ; अथ: एक कपड़घर। a tent-house. ; English: a tent-house ; ु प : [VR]"},{"i":31889,"h":"खोर- वध","b":"[ व.] ; अथ: वशेष लुतुकवाला (जैसे गँजखोर, भतखोर, मदखोर) ; े : वभाव ; र ज टर: मै."},{"i":31890,"h":"खोर खरय","b":"[n.] ; अथ: म थलाक भोजन-श दावलीक ‘इआ/इआँ’ यययु त श द। ; English: Mithila food-vocabulary iā-suﬃx term ; े : भोजन/पाक"},{"i":31891,"h":"खोरन","b":"[n.] ; अथ: आ ग बाहर-भीतर करबाक वृ ा दक द ड। ; English: ﬁre-poking stick ; े : ाणी/ वन प त"},{"i":31892,"h":"खोरन","b":"[n.] ; अथ: खोरनाक पा तर। ; English: ﬁre-poking stick variant"},{"i":31893,"h":"खोरन","b":"[n.] ; अथ: चू हमे पात झाकबाक का खंड। ; English: wooden poker for feeding leaves ; े : ाणी/वन प त"},{"i":31894,"h":"खोरन","b":"[n.] ; अथ: धनउ स नयाँमे आ ग बाहर-भीतर करबाक द ड ; English: ﬁre-adjusting stick"},{"i":31895,"h":"खोरन","b":"[n.] ; अथ: यय-योजनासँ मशः बनल श द- ंखला। ; English: derivational chain example ; े : सा ह य/ ाकरण"},{"i":31896,"h":"खोरन","b":"[n.] ; अथ: भोजन-श दावलीमे एका धक यय- योगक उदाहरण। ; English: example of multiple suﬃxation in food vocabulary ; े : भोजन/पाक"},{"i":31897,"h":"खोरना-स","b":"[सं.] ; अथ: कोनो व तु क ं चालैक आ उपर नीचाँ को ड को ड व थत करैक साधन ; े : उपकरण ; र ज टर: मै."},{"i":31898,"h":"खोरनाठ","b":"[n.] ; अथ: खोरनाक पा तर। ; English: wooden poker variant"},{"i":31899,"h":"खोरनाठ","b":"[n.] ; अथ: यय-योजनासँ मशः बनल श द- ंखला। ; English: derivational chain example ; े : सा ह य/ ाकरण"},{"i":31900,"h":"खोरनाठ","b":"[n.] ; अथ: भोजन-श दावलीमे एका धक यय-योगक उदाहरण। ; English: example of multiple suﬃxation in food vocabulary ; े : भोजन/पाक"},{"i":31901,"h":"खोरनाठब","b":"[n.] ; अथ: यय-योजनासँ मशः बनल श द- ंखला। ; English: derivational chain example ; े : सा ह य/ ाकरण"},{"i":31902,"h":"खोरनाठब","b":"[v.] ; अथ: खोरबक पा तर। ; English: to poke embers variant"},{"i":31903,"h":"खोरब","b":"[v.] ; अथ: राख ओ इंधन आ दक े चलायमान करबाक या। ; English: to poke/stir embers"},{"i":31904,"h":"खोरब-","b":"[ .] ; अथ: १. ढ ल आ ठोस क ं कोडब; २. उपे लत वषय क े य मे आनब; ३. बात क ं बार बार उठाएब ; े : या ; र ज टर: मै."},{"i":31905,"h":"खोरह","b":"[n.] ; देखू: देखू: भजहा। मूल व म संद भत प ; े : क ृ ष/लोक-श दावली"},{"i":31906,"h":"खोरह","b":"[n] ; अथ: एक पशु रोग। a cattle disease. ; English: a cattle disease"},{"i":31907,"h":"खोराक","b":"[n] ; अथ: 1. औषधक मा ा। dose. 2. आहार, भोजनमा ा। diet. diet allowance. ; English: dose; diet, diet allowance ; यौ गक: खोराक n भोजन-भ ा। ; ु प : [P]"},{"i":31908,"h":"खोराजाल","b":"[n.] ; अथ: पूरा हरौत बाँसक ल गा लागल बसेर जाल। ; English: baser net with a whole green bamboo pole"},{"i":31909,"h":"खोराजाल","b":"[n.] ; अथ: साँसे हरौत बाँसक ल गा लागल बसेर जाल। ; English: Baser net ﬁtted with full-length green bamboo poles."},{"i":31910,"h":"खोरासान","b":"अथ: See खुरासानी। ; देखू: See खुरासानी"},{"i":31911,"h":"खो रश","b":"[n.] ; देखू: देखू: खानदान। मूल व म संद भत प ; े : क ृ ष/लोक-श दावली"},{"i":31912,"h":"खो रश","b":"[n.] ; देखू: देखू: परवसती। मूल व म संद भत प ; े : क ृ ष/लोक-श दावली"},{"i":31913,"h":"खो रश","b":"[n.] ; देखू: देखू: पालक। मूल व म संद भत प ; े : क ृ ष/लोक-श दावली"},{"i":31914,"h":"खो रश","b":"[n.] ; देखू: देखू: सोकर । मूल व म संद भत प ; े : क ृ ष/लोक-श दावली"},{"i":31915,"h":"खो रस","b":"[n] ; अथ: नवाह-भ ा। maintenance allowance spl to a widow. ; English: maintenance allowance spl to a widow ; ु प : [P]"},{"i":31916,"h":"खोल","b":"[n.] ; अथ: अंद नी वभागक प। ; English: Compartment; variant."},{"i":31917,"h":"खोल","b":"[n.] ; अथ: को घुमाबयबला बड़दक आँ खपर ब हल प ी। ; English: blindfold for oil-press bullock ; े : क ृ ष/लोक-श दावली"},{"i":31918,"h":"खोल","b":"[n.] ; अथ: खरादमे यु त खानीक एक कार। ; English: Lathe chisel type."},{"i":31919,"h":"खोल","b":"[n.] ; अथ: खोलक प; व क आवरण। ; English: cover or casing variant ; े : व / सलाइ"},{"i":31920,"h":"खोल","b":"[n.] ; अथ: खोलक पा तर; वा यं क मा टक आधार। ; English: earthen resonator variant ; े : क ृ ष/लोक-श दावली"},{"i":31921,"h":"खोल","b":"[n.] ; अथ: खोलक पा तर। ; English: variant of cover/casing"},{"i":31922,"h":"खोल","b":"[n.] ; अथ: खोलक प। ; English: cover/ casing variant"},{"i":31923,"h":"खोल","b":"[n.] ; अथ: खोलक प। ; English: Earthen musical-instrument base; variant."},{"i":31924,"h":"खोल","b":"[n.] ; अथ: खोलाक प; खरादक खानी। ; English: Lathe chisel; variant."},{"i":31925,"h":"खोल","b":"[n.] ; अथ: खोलाक प। ; English: Compartment; variant."},{"i":31926,"h":"खोल","b":"[n.] ; अथ: तीन कात सीयल दोहरा व जकर भीतर तूर भरल जाइत अ छ। ; English: cover/ casing for ﬁlling cotton ; े : व / सलाइ"},{"i":31927,"h":"खोल","b":"[n.] ; अथ: तूर भरबाक हेतु काते-कात सीयल दोहरा व क आवरण। ; English: casing/cover for ﬁlling cotton ; े : व / सलाइ"},{"i":31928,"h":"खोल","b":"[n.] ; अथ: र अ ु प न श दक उदाहरण। ; English: disyllabic example"},{"i":31929,"h":"खोल","b":"[n.] ; अथ: यालाक पा तर। ; English: variant of bowl-like vessel"},{"i":31930,"h":"खोल","b":"[n.] ; अथ: यालाक प। ; English: Deep bowl-like vessel; variant."},{"i":31931,"h":"खोल","b":"[n.] ; अथ: व तु पैसबाक खोल; सीड़क , तोशक, गेडुआ आ दक आवरण। ; English: cover/casing"},{"i":31932,"h":"खोल","b":"[n.] ; अथ: वा -यं क मा टसँ बनल गोलाधार आधार। ; English: Earthen bowl-like base of a musical instrument. ; े : क ृ ष/लोक- श दावली"},{"i":31933,"h":"खोल","b":"[n.] ; अथ: वा यं क मा टसँ बनल गोला ाकार आधार। ; English: earthen resonator base of instrument ; े : क ृ ष/लोक-श दावली"},{"i":31934,"h":"खोल","b":"[n.] ; अथ: सीड़क, तोशक, गेडुआ आ द पर चढ़ाओल बाहर आवरण। ; English: cover/casing for bedding items"},{"i":31935,"h":"खोल","b":"[n.] ; देखू: देखू - टोकल ; े : क ृ ष/लोक- श दावली"},{"i":31936,"h":"खोल","b":"[n.] ; देखू: देखू --अनपड ; े : क ृ ष/लोक- श दावली"},{"i":31937,"h":"खोल","b":"[n.] ; देखू: देखू बोदर ; े : क ृ ष/लोक-श दावली"},{"i":31938,"h":"खोल","b":"[n] ; अथ: 1. को ाकार बाहर झपना। casing, cover, sheath. 2. को । closet, cell. 3. मआन। case. 4. खोड़, खा ध। cavity. ; English: casing, cover, sheath; closet, cell; case; cavity ; यौ गक: °कड़ा n मोमब ी बनएबाक साँच। mould for making paraﬁn candle sticks. -मड़ेआ n सोनारक एक हथौड़ । a kind of hammer used by goldsmiths."},{"i":31939,"h":"खोल","b":"[n] ; अथ: खोलू ; English: open"},{"i":31940,"h":"खोल","b":"ु प : d of खोल"},{"i":31941,"h":"खोल-स","b":"[सं.] ; अथ: कोनो व तु सुर त रखैक आवरण ; े : व तु ; र ज टर: मै."},{"i":31942,"h":"खोलड","b":"[n.] ; देखू: देखू -- ` लोप ; े : क ृ ष/लोक- श दावली"},{"i":31943,"h":"खोलड","b":"[n.] ; देखू: देखू -खोइया ; े : क ृ ष/लोक- श दावली"},{"i":31944,"h":"खोलड","b":"[n.] ; देखू: देखू -गोथार ; े : क ृ ष/लोक- श दावली"},{"i":31945,"h":"खोलन","b":"[n.] ; अथ: खलनीक पा तर। ; English: round-tip graver variant"},{"i":31946,"h":"खोलन","b":"[n.] ; अथ: गरम सटल चूड़ सभ अलग करबाक प र। ; English: separator tool for stuck bangles"},{"i":31947,"h":"खोलनैय","b":"[n.] ; अथ: अ य त छोट नाओक अ य भेद। ; English: Very small boat; variant/type."},{"i":31948,"h":"खोलनैय","b":"[n.] ; अथ: अ य त छोट नाओक भेद। ; English: very small boat type"},{"i":31949,"h":"खोलब","b":"[vt] ; अथ: ब धन/आवरण हटाएब। open, untie, expose. ; English: open, untie, expose ; यौ गक: खोलनी n सोनारक एक उपकरण। a pulling instrument used by gold-smiths."},{"i":31950,"h":"खोलब","b":"अथ: See खलबलाएब। ; देखू: See खलबलाएब"},{"i":31951,"h":"खोलब-","b":"[ .] ; अथ: १. मु त करब; २. ब धन छोड़ाएब; ३. काश मे आनब; ४. अक ु त करब; ५. अनावृत करब ; े : या ; र ज टर: मै."},{"i":31952,"h":"खोलम रय","b":"[n.] ; अथ: गोलाकार मुँहवला मरेया। ; English: round-faced hammer"},{"i":31953,"h":"खोलस","b":"[n.] ; अथ: खोलाक पा तर। ; English: variant of bullock blindfold"},{"i":31954,"h":"खोलस","b":"[n.] ; देखू: देखू - टोकल ; े : क ृ ष/लोक- श दावली"},{"i":31955,"h":"खोलस","b":"[n.] ; देखू: देखू अनपट परया०- टोकनी, खोलसा ; े : क ृ ष/लोक-श दावली"},{"i":31956,"h":"खोलस","b":"[n.] ; देखू: देखू: अँ धयार । मूल व म संद भत प ; े : क ृ ष/लोक-श दावली"},{"i":31957,"h":"खोलस","b":"[n] ; अथ: घोड़ा आ दक आँ खझपना। eye- band for covering the eyes of animals. ; English: eye-band for covering the eyes of animals"},{"i":31958,"h":"खोलसा 1","b":"[n.] ; अथ: पयाय: ऑलमुँदनी। मूल अथ: मवे ञया क आँख ढॅकने क े लेल बास क कमानी का बना जा ढ न, जमक े .ऊपर कपड़ा मढ़ा रहता ह| पयाय-प र, ट पर, छोपनी, टोकनी— 6 fe, खोलसा (बण) 1 ; े : व / सलाइ"},{"i":31959,"h":"खोलसा-स","b":"[सं.] ; अथ: मुखौटा, मुह बेदरंग करैक खोल ; े : व /सजावट ; र ज टर: मै."},{"i":31960,"h":"खो लआ","b":"[n] ; अथ: एक कारक खान। a chisel. ; English: a chisel"},{"i":31961,"h":"खो लय","b":"[n.] ; अथ: खोलक पा तर। ; English: variant of cover/casing"},{"i":31962,"h":"खो लय","b":"[n.] ; अथ: खोलक प। ; English: cover/casing variant"},{"i":31963,"h":"खो लय","b":"[n.] ; अथ: चा र मु य खरादी खानीमे एक कार। ; English: One type of lathe chisel."},{"i":31964,"h":"खोव","b":"[n.] ; अथ: मै थलीक भोजन-श दावलीक व न- वचार स ब धी श द। ; English: phonological term or example in Maithili food vocabulary ; े : भोजन/पाक"},{"i":31965,"h":"खोवल","b":"[n.] ; अथ: म थलाक उपकरण/बासन श द। ; English: Mithila utensil/vessel term ; े : भोजन/पाक"},{"i":31966,"h":"खोष","b":"[n.] ; अथ: क ृ यय- नमाणक आधार प। ; English: base form for suﬃxal derivation ; े : सा ह य/ ाकरण"},{"i":31967,"h":"खोसन","b":"[n.] ; अथ: चाभीक समूह डाँड़मे लटकाकऽ रखबाक नक ु शीयु त चानीक गहना। ; English: waist key-holder ornament"},{"i":31968,"h":"खोसन","b":"[n.] ; अथ: चाभीक समूह राखयवला चानीक गहना। ; English: Silver key-holder ornament."},{"i":31969,"h":"खोह","b":"[n.] ; English: cave"},{"i":31970,"h":"खोह","b":"[n.] ; English: heap of crop kept for threshing"},{"i":31971,"h":"खोह","b":"[n] ; अथ: दाउ नक हेतु राखल फ सलक ढेर। heap of crop kept for threshing. ; English: heap of crop kept for threshing ; यौ गक: ~ तरसँ बेचब vt खारहा न हसँ बनु सुखओ नह अनाज बेचब। dispose of grains on the threshing yard."},{"i":31972,"h":"खोहब","b":"[vt.] ; English: to carve"},{"i":31973,"h":"खोहब","b":"[vt] ; अथ: को ड़क भीतर पैसब। dig and enter into. ; English: dig and enter into ; ु प : [शोद-]"},{"i":31974,"h":"खोहर","b":"[n] ; अथ: छोट गुहा। cavity. ; English: cavity"},{"i":31975,"h":"खो हय","b":"[n.] ; देखू: देखू खोइया ; े : क ृ ष/लोक- श दावली"},{"i":31976,"h":"खो या { पड०. णय","b":"[n.] ; देखू: देखू -- ` लोप ; े : ृ ष/लोक-श दावली"},{"i":31977,"h":"खाछ","b":"[n] ; अथ: कपड़ाक कोन जो ड़ बनाओल झोड़ा। bag devised by joining two ends of napkin. ; English: bag devised by joining two ends of napkin"},{"i":31978,"h":"खाझाएब","b":"[vi] ; अथ: ख सआएब, भतर ह भतर होएब। be annoyed. ; English: be annoyed ; यौ गक: खाझ n."},{"i":31979,"h":"खाड","b":"[n.] ; English: (, 7. (nonhon. boy"},{"i":31980,"h":"खाड़ाछौड","b":"[n.] ; English: (nonhon. boy and girl"},{"i":31981,"h":"खाझाएब","b":"[vi.] ; English: to be irritated"},{"i":31982,"h":"खौआ","b":"[adj] ; अथ: खाधुर। voracious. ; English: voracious"},{"i":31983,"h":"खौआ-बजौआ","b":"[n] ; अथ: अ नदाताक गुणगान कर नहार। eloquent in praising one's supporter. ; English: eloquent in praising one's supporter"},{"i":31984,"h":"खौक","b":"[adj.] ; English: voracious ; समानाथ : कओरगर"},{"i":31985,"h":"खौक","b":"[adj] ; अथ: 1. अ धक खए नहार, पेटू। voracious. 2. आनक धन वा ऋण पचओ नहार। one who digests loan or other's things. ; English: voracious; one who digests loan or other's things ; देखू: Also खौकाड़, कौकाड़ा."},{"i":31986,"h":"खौकाड","b":"[adj.] ; English: gluttonous"},{"i":31987,"h":"खौड़क","b":"[n.] ; English: a small girl's dress"},{"i":31988,"h":"खौत","b":"[n] ; अथ: वाला। burning sensation, scorching heat, hotness. ; English: burning sensation, scorching heat, hotness"},{"i":31989,"h":"खौबाढ़न","b":"[n] ; अथ: खाएबाक पाछाँ स प गमओ नहार। squanderer, one who spends much on eating and drinking. ; English: squanderer, one who spends much on eating and drinking"},{"i":31990,"h":"खौर","b":"[n.] ; देखू: देखू: खडरा। मूल व म संद भत प ; े : क ृ ष/लोक-श दावली"},{"i":31991,"h":"खौर","b":"[n] ; अथ: शौर, नह-क े स। shaving and cutting nails for puriﬁcation. ; English: shaving and cutting nails for puriﬁcation"},{"i":31992,"h":"खौरछाइन","b":"[adj.] ; अथ: भोजनक काय- ापार, वशेष भोज, च वा वाद-स दभक श द। ; English: food practice, special meal, appetite, or taste term ; े : भोजन/पाक"},{"i":31993,"h":"खौरछाह","b":"[adj.] ; अथ: भोजनक काय- ापार, वशेष भोज, च वा वाद-स दभक श द। ; English: food practice, special meal, appetite, or taste term ; े : भोजन/पाक"},{"i":31994,"h":"खौरब","b":"[vt.] ; English: to shave.; vi. to boil"},{"i":31995,"h":"खौल","b":"[n.] ; English: fun, joke"},{"i":31996,"h":"खौ लआ","b":"[adj.] ; English: funny"},{"i":31997,"h":"खौस","b":"[n.] ; English: 5 YA (vn. ball-like"},{"i":31998,"h":"खौस","b":"[n.] ; English: scabies"},{"i":32015,"h":"ख्ि◌ल खलाएब","b":"[vi.] ; English: to chuckle"},{"i":32016,"h":"ख्◌ुआ","b":"[n.] ; देखू: देखू: खेप। मूल व म संद भत प ; े : क ृ ष/लोक-श दावली"},{"i":42236,"h":"े खाय","b":"[n./phrase] ; अथ: लोकसा ह य/ लोको त भोजन- व यास-स दभक श द। ; English: folk-literature/proverbial food- arrangement term ; े : भोजन/पाक"},{"i":47362,"h":"ख नता; अवसाद सराबोर","b":"बु झ"},{"i":53505,"h":"े खूट","b":"[n.] ; अथ: जोलहाक द हना भागक खु ा। ; English: Right-side rope-tying post of a weaver's loom."},{"i":60599,"h":":ख","b":"[n] ; अथ: तकलीफ, क ; pain, distress, sorrow, regret, grief ; English: pain, distress, sorrow, regret, grief ; देखू: ख Also"},{"i":60604,"h":"ःख","b":"[adj.] ; English: unhappy, sorry, wretched, sad;; vi. to be sad"},{"i":60605,"h":"ःख","b":"[n.] ; English: gallery, corridor"},{"i":60606,"h":"ःख","b":"[n.] ; English: pain, touble, adversity"},{"i":60607,"h":"ःख","b":"[n.] ; English: sorrow ; समानाथ : असुख; अफसोच"},{"i":60608,"h":"ःख","b":"[n.] ; English: unhappy ; समानाथ : बेखुशी"},{"i":60609,"h":"ःखब","b":"[vi.] ; English: to ache"},{"i":60610,"h":"ःखा त नाटक","b":"[n.] ; English: tragedy ; समानाथ : ासदी"},{"i":60611,"h":"ः खत","b":"[adj.] ; English: sorry, ailing, sick, sorry"},{"i":60612,"h":"ः खत","b":"[n.] ; English: sorry"},{"i":60613,"h":"ःखीय","b":"[n.] ; English: suﬀerer"},{"i":60614,"h":"ःखीय","b":"English: dul"},{"i":60656,"h":"ख","b":"[n] ; अथ: See :खा; रोग, अ व थता; sickness, disease ; English: sickness, disease ; यौ गक: देब vt सताएब oppress, harass; खाएने अपकार करब, अप य होएब be harmful (said of victuals); बेकाल rep. See खनामा; खद adj क दायक, शोक द uncomfortable, sad; खनामा n था-कथा tale of one's suﬀerings; खाएब vi वेदना द होएब ache, be painful; खा त adj कहण अ तबाला (का ) ending in tragedy; खआ See खी; खत, खताह adj अ व थ, रोगी sick; खी adj पी ड़त, क मे पड़ल distressed, aggrieved"},{"i":60657,"h":"खनाम","b":"[n.] ; English: apprehension -; vi. to apprehend"},{"i":60658,"h":"खनाम","b":"[n.] ; English: tale of grievance"},{"i":60659,"h":"खब","b":"[vt.] ; English: to suﬀer from stomachache"},{"i":60660,"h":"खाएब","b":"[n.] ; English: spotted panther | citr. 7. picture, ﬁgure"},{"i":60661,"h":"खत","b":"[n.] ; English: ailing ; समानाथ : रोगाएल 'ल"},{"i":60662,"h":"खीय","b":"[n.] ; English: suﬀerer"},{"i":60925,"h":"ख","b":"[n.] ; अथ: फारसीमूलक गृहीत श दक उदाहरण। ; English: Persian-origin loanword example"},{"i":60926,"h":"ख","b":"[n.] ; अथ: बाहर दरव जा परक चौक ठ। ; English: Outer door frame."},{"i":61105,"h":"खन","b":"[obs n] ; अथ: षण, दोष ; English: blame"},{"i":62425,"h":"ेख","b":"[n] ; अथ: वर त, घृणा; repugnance, abhorence, hatred; अ हत-कामना ill will, malice; श ुता enmity ; English: repugnance, abhorence, hatred; ill will, malice; enmity"},{"i":77583,"h":"खर","b":"[adj.] ; English: violent, acrid"},{"i":77584,"h":"खर","b":"[adj.] ; English: violent, acrid a"},{"i":77585,"h":"खर","b":"[adj] ; अथ: तेज, ती , उ कट ; English: sharp, strong, keen"},{"i":77586,"h":"खर छ न भ न ओढ़ना मुठ","b":"[n.] ; English: sharpness"},{"i":77587,"h":"खरत","b":"[n.] ; English: sharpness, severity"},{"i":77588,"h":"खरत","b":"[n.] ; English: sharpness, | ess, severity"},{"i":78599,"h":"ाख","b":"[n.] ; देखू: देखू: गे ठया। मूल व म संद भत प ; े : क ृ ष/लोक-श दावली"},{"i":80141,"h":"ु खाठ","b":"[n.] ; अथ: आ ग फ ु कबाक बाँस अथवा लोहक नली। ; English: blowpipe for stoking ﬁre"},{"i":89500,"h":"ाखर","b":"[n.] ; अथ: नवास-घर, हवेली, बखार । का मादा ब चा। पयाय--ब छया। (२) गाय क [वखर (१)। मला क वा ह | बया ; े : क ृ ष/लोक-श दावली"},{"i":96546,"h":"े खाए","b":"[n./phrase] ; अथ: लोकसा ह य/ लोको त भोजन- व यास-स दभक श द। ; English: folk-literature/proverbial food- arrangement term ; े : भोजन/पाक"},{"i":103040,"h":"ख","b":"[adj.] ; अथ: कम गील, खड़ा मा टक दशा। ; English: dryish/less-wet clay state ; े : ृ ष/लोक-श दावली"},{"i":103041,"h":"ख","b":"[adj] ; अथ: 1. ख, आईतासँ र हत (भात, मा ट आ द)। 2. सन धतासँ र हत, खरखर। ; English: 1. dry. 2. rough, astringent, harsh ; यौ गक: वप न कन"},{"i":103042,"h":"ख","b":"[Adjective/Noun] ; अथ: कम गील मा ट। ; English: Dryish/stiﬀ clay. ; े : क ृ ष/लोक- श दावली"},{"i":103043,"h":"ख","b":"[n.] ; अथ: पेड़। क कवल सौ वष पहेले ही यह बाहर से भारत (, | | आया हो \\ ; े : क ृ ष/लोक- श दावली"},{"i":103045,"h":"ख","b":"[adj] ; अथ: See ख ; English: सुख n जनहीन रसहीन द र ो चत (भोजन) ; यौ गक: (food) dry and devoid of all relish"},{"i":103046,"h":"ख","b":"[n [P]] ; अथ: 1. मुह वा मु य भागक दशा, सा मु य। 2. मुहक छ व/भाव। 3. काओ, वृ । 4. स मुख दसक अवकाश। ; English: 1. face-side, frontage. 2. countenance, attitude. 3. tendency, trend. 4. open space/clearance on the front side, vantage ; यौ गक: खगर adj सामने खुलता जगहबाला (भवन आ द)"},{"i":103047,"h":"ख","b":"[n.] ; English: azar frontage"},{"i":103048,"h":"ख","b":"[n.] ; English: mouth, face"},{"i":103049,"h":"ख","b":"[n.] ; अथ: वृ ा पर रहनेवाला एक स जीव, | 2 | इना_(सं०) ओ खेत, जसम सचाई क आव यकता.. F | [हो (द० मु ०-१) रंड_(सं०) (१) एक स पौधा, जसको फली स ||| [इना (देशो) वा < ड-(१); मला०- लु, नको तेल नकलता अ छ, अंड । (२) इस पौधे क फली। रेती- ||| यह पौधा, बार या खेत दोना जगहा म होइत अ छ ; े : क ृ ष/लोक-श दावली"},{"i":103050,"h":"ख बड","b":"[n./phrase] ; अथ: दा ल, बेसन वा द लहन- ंजन स ब धी श द। ; English: pulse or gram- ﬂour dish term ; े : भोजन/पाक"},{"i":103051,"h":"खाण","b":"[n.] ; अथ: खूब चाकर फलकवला नेहनी। ; English: very broad-bladed scraper"},{"i":103052,"h":"खाण","b":"[n.] ; अथ: खूब चाकर फलवला नेहनी। ; English: broad scraper"},{"i":103053,"h":"खाण","b":"[n.] ; अथ: तेल पेड् बाक बाद को सँ अवशेष बाहर करबाक लोहक औजार। ; English: iron tool for removing oilcake residue"},{"i":103054,"h":"खान","b":"[n.] ; English: chisel @t"},{"i":103055,"h":"खान","b":"[n.] ; अथ: लकड़ मे न त ग हराइ आ चौड़ाइ ध र छेद करबाक औजार। ; English: Chisel used to make and clean recesses in wood."},{"i":103056,"h":"खान","b":"[n] ; अथ: काठमे खाँच बनएबाक एक ह थयार ; English: chisel ; यौ गक: खानी d."},{"i":103144,"h":"ख","b":"[n.] ; अथ: दरसक प; प लाक सामने भाग। ; English: Front face; variant."},{"i":103145,"h":"ख","b":"[n.] ; अथ: खक प। ; English: Front face; variant."},{"i":103146,"h":"खासान","b":"[n.] ; अथ: कलम ती ण करबाक चौखूट खुर राह सान। ; English: rough sharpening stone"},{"i":111565,"h":"ख ड","b":"[n.] ; English: audible segment. n. auditory language -. n. audio- visual adj. audio- visual"},{"i":111566,"h":"ख ड","b":"[n.] ; English: d, audible segment"},{"i":111604,"h":"ीख ड","b":"[n./phrase] ; अथ: ाचीन भोजन-पर परामे यु त खा , पेय वा स ब धत श द। ; English: ancient food-tradition term ; े : भोजन/ पाक"},{"i":111605,"h":"ीख ड","b":"[n.] ; अथ: च दनक एक भेद। ; English: A variety of sandalwood. ; े : भोजन/पाक"},{"i":111623,"h":"ृंखल","b":"[n.] ; English: sequence ; समानाथ : अनु म ृङ"},{"i":121829,"h":"खल","b":"[adv.] ; English: srately, di * throw Separately iﬀerently. aa"},{"i":121830,"h":"खलन","b":"[n.] ; English: sensation ; समानाथ : संवेदन"},{"i":121831,"h":"खलन","b":"[n.] ; English: stock"},{"i":121832,"h":"खलन","b":"[n] ; अथ: 1. खसनाइ, युत भेनाइ। 2. चूक, ु ट। 3. चुनाइ, वण। 4. वचलन ; English: 1. fall, slip. 2. fault. 3. discharge, oozing, emission. 4. deviation"},{"i":126979,"h":"खंडन करब","b":"समानाथ : उखाड़ब ; English: refute ; English synonym: overthrow"},{"i":126980,"h":"खंडन करब","b":"समानाथ : खंडन करब ; English: refute ; English synonym: confute"},{"i":126981,"h":"खंडन करब","b":"समानाथ : खंडन करब ; English: refute ; English synonym: disprove"},{"i":126982,"h":"खंडन करब","b":"समानाथ : मत करब ; English: refute ; English synonym: confound"},{"i":126983,"h":"खंडन करब","b":"समानाथ : रोकब ; English: refute ; English synonym: repel"},{"i":126984,"h":"खर दब","b":"समानाथ : अदल-बदल करब ; English: purchase ; English synonym: barter for"},{"i":126985,"h":"खर दब","b":"समानाथ : कनब ; English: purchase ; English synonym: bargain for"},{"i":126986,"h":"खर दब","b":"समानाथ : कनब ; English: purchase ; English synonym: buy"},{"i":126987,"h":"खर दब","b":"समानाथ : पाएब ; English: purchase ; English synonym: get"},{"i":126988,"h":"खर दब","b":"समानाथ : ा त करब ; English: purchase ; English synonym: acquire"},{"i":126989,"h":"खर दब","b":"समानाथ : ा त करब ; English: purchase ; English synonym: obtain"},{"i":126990,"h":"खर दब","b":"समानाथ : ा त करब ; English: purchase ; English synonym: procure"},{"i":126991,"h":"खर दब","b":"समानाथ : सुर त ; English: purchase ; English synonym: secure"},{"i":126992,"h":"खच","b":"समानाथ : खच ; English: expense ; English synonym: expenditure"},{"i":126993,"h":"खच","b":"समानाथ : खच ; English: expense ; English synonym: outgo"},{"i":126994,"h":"खच","b":"समानाथ : खच ; English: expense ; English synonym: outlay"},{"i":126995,"h":"खच","b":"समानाथ : मू ; English: expense ; English synonym: cost"},{"i":126996,"h":"खाल","b":"समानाथ : unemployल ; English: vacant ; English synonym: unemployed"},{"i":126997,"h":"खाल","b":"समानाथ : unﬁllल ; English: vacant ; English synonym: unﬁlled"},{"i":126998,"h":"खाल","b":"समानाथ : unoccupiल ; English: vacant ; English synonym: unoccupied"},{"i":126999,"h":"खाल","b":"समानाथ : untenantल ; English: vacant ; English synonym: untenanted"},{"i":127000,"h":"खाल","b":"समानाथ : vacuयु त ; English: vacant ; English synonym: vacuous"},{"i":127001,"h":"खाल","b":"समानाथ : खाली ; English: vacant ; English synonym: blank"},{"i":127002,"h":"खाल","b":"समानाथ : खाली ; English: vacant ; English synonym: empty"},{"i":127003,"h":"खाल","b":"समानाथ : खाली ; English: vacant ; English synonym: void"},{"i":127004,"h":"खाल","b":"समानाथ : खाली समय ; English: vacant ; English synonym: leisure"},{"i":127005,"h":"खाल","b":"समानाथ : बबाद करब ; English: vacant ; English synonym: waste"},{"i":127006,"h":"ख नत","b":"समानाथ : mortiﬁcatन ; English: chagrin ; English synonym: mortiﬁcation"},{"i":127007,"h":"ख नत","b":"समानाथ : vexatन ; English: chagrin ; English synonym: vexation"},{"i":127008,"h":"ख नत","b":"समानाथ : अपमा नत करबन ; English: chagrin ; English synonym: humiliation"},{"i":127009,"h":"ख नत","b":"समानाथ : नराश करब ; English: chagrin ; English synonym: dismay"},{"i":127010,"h":"ख नत","b":"समानाथ : नराश करबन ; English: chagrin ; English synonym: disappointment"},{"i":127011,"h":"ख नत","b":"समानाथ : म ; English: chagrin ; English synonym: confusion"},{"i":127012,"h":"ख नत","b":"समानाथ : ल जा ; English: chagrin ; English synonym: shame"},{"i":127013,"h":"ख नत","b":"समानाथ : वचलन ; English: chagrin ; English synonym: discomposure"},{"i":127014,"h":"ख चब","b":"समानाथ : आक षत करब ; English: draw ; English synonym: attract"},{"i":127015,"h":"ख चब","b":"समानाथ : ख चब ; English: draw ; English synonym: drag"},{"i":127016,"h":"ख चब","b":"समानाथ : ख चब ; English: draw ; English synonym: haul"},{"i":127017,"h":"ख चब","b":"समानाथ : ख चब ; English: draw ; English synonym: pull"},{"i":127018,"h":"ख चब","b":"समानाथ : ख चब ; English: draw ; English synonym: tow"},{"i":127019,"h":"ख चब","b":"समानाथ : ख चब ; English: draw ; English synonym: tug"},{"i":127020,"h":"ख चब","b":"समानाथ : काव ; English: draw ; English synonym: incline"},{"i":127021,"h":"ख चब","b":"समानाथ : नेतृ व करब ; English: draw ; English synonym: lead"},{"i":127022,"h":"ख चब","b":"समानाथ : े रत करब ; English: draw ; English synonym: induce"},{"i":127023,"h":"ख चब","b":"समानाथ : लुभाएब ; English: draw ; English synonym: allure"},{"i":127024,"h":"ख चब","b":"समानाथ : लुभाएब ; English: draw ; English synonym: entice"},{"i":127025,"h":"ख चब","b":"समानाथ : लुभाएब ; English: draw ; English synonym: lure"},{"i":127026,"h":"खेत","b":"समानाथ : farmब ; English: agriculture ; English synonym: farming"},{"i":127027,"h":"खेत","b":"समानाथ : gardenब ; English: agriculture ; English synonym: gardening"},{"i":127028,"h":"खेत","b":"समानाथ : kitchen-gardenब ; English: agriculture ; English synonym: kitchen- gardening"},{"i":127029,"h":"खेत","b":"समानाथ : market-gardenब ; English: agriculture ; English synonym: market- gardening"},{"i":127030,"h":"खेत","b":"समानाथ : खेती ; English: agriculture ; English synonym: husbandry"},{"i":127031,"h":"खेत","b":"समानाथ : खेती ; English: agriculture ; English synonym: tillage"},{"i":127032,"h":"खेत","b":"समानाथ : खेती करबन ; English: agriculture ; English synonym: cultivation"},{"i":127033,"h":"खेत","b":"समानाथ : फ ू ला क खेती ; English: agriculture ; English synonym: ﬂoriculture"},{"i":127034,"h":"खेत","b":"समानाथ : बागवानी ; English: agriculture ; English synonym: horticulture"},{"i":127035,"h":"खेत","b":"समानाथ : सं क ृ त ; English: agriculture ; English synonym: culture"},{"i":127911,"h":"ख","b":"समानाथ : melanchoसँ ; English: grief ; English synonym: melancholy"},{"i":127912,"h":"ख","b":"समानाथ : tribulatन ; English: grief ; English synonym: tribulation"},{"i":127913,"h":"ख","b":"समानाथ : खेद ; English: grief ; English synonym: regret"},{"i":127914,"h":"ख","b":"समानाथ : ख ; English: grief ; English synonym: sorrow"},{"i":127915,"h":"ख","b":"समानाथ : ख ; English: grief ; English synonym: wo"},{"i":127916,"h":"ख","b":"समानाथ : खीता ; English: grief ; English synonym: sadness"},{"i":127917,"h":"ख","b":"समानाथ : परेशानी ; English: grief ; English synonym: trouble"},{"i":127918,"h":"ख","b":"समानाथ : पीड़ा ; English: grief ; English synonym: aﬄiction"},{"i":127919,"h":"ख","b":"समानाथ : पीड़ा ; English: grief ; English synonym: distress"},{"i":127920,"h":"ख","b":"समानाथ : शोक करब ; English: grief ; English synonym: mourning"},{"i":130811,"h":"ृंखल","b":"समानाथ : collectन ; English: array ; English synonym: collection"},{"i":130812,"h":"ृंखल","b":"समानाथ : dispositन ; English: array ; English synonym: disposition"},{"i":130813,"h":"ृंखल","b":"समानाथ : exhibitन ; English: array ; English synonym: exhibition"},{"i":130814,"h":"ृंखल","b":"समानाथ : आदेश ; English: array ; English synonym: order"},{"i":130815,"h":"ृंखल","b":"समानाथ : जुलूस ; English: array ; English synonym: parade"},{"i":130816,"h":"ृंखल","b":"समानाथ : दखाएब ; English: array ; English synonym: show"},{"i":130817,"h":"ृंखल","b":"समानाथ : य ; English: array ; English synonym: sight"},{"i":130818,"h":"ृंखल","b":"समानाथ : यु रेखा ; English: array ; English synonym: line of battle"},{"i":130819,"h":"ृंखल","b":"समानाथ : यु ूह ; English: array ; English synonym: order of battle"},{"i":130820,"h":"ृंखल","b":"समानाथ : व था ; English: array ; English synonym: arrangement"},{"i":130821,"h":"ृंखल","b":"समानाथ : ूह ; English: array ; English synonym: battle array"},{"i":130822,"h":"ृंखल","b":"समानाथ : सेना ; English: array ; English synonym: army"},{"i":132579,"h":"खर दब","b":"वलोम: नपटाएब ; English: purchase ; English antonym: dispose of"},{"i":132580,"h":"खर दब","b":"वलोम: बेचब ; English: purchase ; English antonym: put to sale"},{"i":132581,"h":"खर दब","b":"वलोम: बेचब ; English: purchase ; English antonym: sell"},{"i":132582,"h":"खर दब","b":"वलोम: व नमय ; English: purchase ; English antonym: barter"},{"i":132583,"h":"खर दब","b":"वलोम: व नमय ; English: purchase ; English antonym: exchange"},{"i":132584,"h":"खच","b":"वलोम: आय ; English: expense ; English antonym: income"},{"i":132585,"h":"खच","b":"वलोम: आय ; English: expense ; English antonym: proceeds"},{"i":132586,"h":"खच","b":"वलोम: आय ; English: expense ; English antonym: receipts"},{"i":132587,"h":"खच","b":"वलोम: आय ; English: expense ; English antonym: returns"},{"i":132588,"h":"खच","b":"वलोम: उ पाद ; English: expense ; English antonym: product"},{"i":132589,"h":"खच","b":"वलोम: ा त ; English: expense ; English antonym: receipt"},{"i":132590,"h":"खच","b":"वलोम: लाभ ; English: expense ; English antonym: gain"},{"i":132591,"h":"खच","b":"वलोम: लाभ ; English: expense ; English antonym: proﬁt"},{"i":132592,"h":"खच","b":"वलोम: लाभ ; English: expense ; English antonym: proﬁts"},{"i":132593,"h":"खच","b":"वलोम: वापस आएब ; English: expense ; English antonym: return"},{"i":132594,"h":"खाल","b":"वलोम: crammल ; English: vacant ; English antonym: crammed"},{"i":132595,"h":"खाल","b":"वलोम: crowdल ; English: vacant ; English antonym: crowded"},{"i":132596,"h":"खाल","b":"वलोम: ﬁllल ; English: vacant ; English antonym: ﬁlled"},{"i":132597,"h":"खाल","b":"वलोम: gorgल ; English: vacant ; English antonym: gorged"},{"i":132598,"h":"खाल","b":"वलोम: inhabitल ; English: vacant ; English antonym: inhabited"},{"i":132599,"h":"खाल","b":"वलोम: jammल ; English: vacant ; English antonym: jammed"},{"i":132600,"h":"खाल","b":"वलोम: occupiल ; English: vacant ; English antonym: occupied"},{"i":132601,"h":"खाल","b":"वलोम: overﬂowब ; English: vacant ; English antonym: overﬂowing"},{"i":132602,"h":"खाल","b":"वलोम: packल ; English: vacant ; English antonym: packed"},{"i":132603,"h":"खाल","b":"वलोम: पूण ; English: vacant ; English antonym: full"},{"i":132604,"h":"खाल","b":"वलोम: भरल ; English: vacant ; English antonym: brimmed"},{"i":132605,"h":"खाल","b":"वलोम: भरल ; English: vacant ; English antonym: replete"},{"i":132606,"h":"खाल","b":"वलोम: लबालब ; English: vacant ; English antonym: brimful"},{"i":132607,"h":"खाल","b":"वलोम: लबालब ; English: vacant ; English antonym: brimming"},{"i":132608,"h":"खाल","b":"वलोम: त ; English: vacant ; English antonym: busy"},{"i":132609,"h":"ख नत","b":"वलोम: exultatन ; English: chagrin ; English antonym: exultation"},{"i":132610,"h":"ख नत","b":"वलोम: आनंद ; English: chagrin ; English antonym: delight"},{"i":132611,"h":"ख नत","b":"वलोम: खुश होएब ; English: chagrin ; English antonym: rejoicing"},{"i":132612,"h":"ख नत","b":"वलोम: जीत ; English: chagrin ; English antonym: triumph"},{"i":132613,"h":"ख नत","b":"वलोम: म हमा ; English: chagrin ; English antonym: glory"},{"i":132614,"h":"ख चब","b":"वलोम: See synonyms for DRIVE ; English: draw ; English antonym: See synonyms for DRIVE"},{"i":132615,"h":"ख चब","b":"वलोम: अलग करब ; English: draw ; English antonym: alienate"},{"i":132616,"h":"ख चब","b":"वलोम: अ वीकार करब ; English: draw ; English antonym: reject"},{"i":132617,"h":"ख चब","b":"वलोम: ठुकराएब ; English: draw ; English antonym: rebuﬀ"},{"i":132618,"h":"ख चब","b":"वलोम: र करब ; English: draw ; English antonym: estrange"},{"i":132619,"h":"ख चब","b":"वलोम: रोकब ; English: draw ; English antonym: repel"},{"i":132620,"h":"ख चब","b":"वलोम: हटाएब ; English: draw ; English antonym: repulse"},{"i":133087,"h":"ख","b":"वलोम: See synonyms for HAPPINESS ; English: grief ; English antonym: See synonyms for HAPPINESS"}]